{
  "code": "A00000",
  "data": {
    "card_type": "catelib_video",
    "pingback": {
      "bkt": "list_D,list_online",
      "e": "ebcd9812f2fc0e6f0b88232f937aae9f"
    },
    "session": "a54d986876288567482c5013b175f9e6",
    "has_next": 1,
    "list": [
      {
        "tvId": 825571200,
        "albumId": 825571200,
        "channelId": 1,
        "description": "影片根据法医秦明小说《尸语者》改编。讲述被誉为“鬼手佛心”的“尸语者”秦明解剖过 1000 多具尸体，从未出错，因意外发现泡在福尔马林里6年的“无语体师”死于他杀，引发媒体质疑误判，被舆论推至风口浪尖之上。在尸体留下的线索指引下，秦明在实习助手嘉嘉和刑警队长林涛的协助调查下发现了尘封 16 年的雪灾杀人案、误判 6 年的“无语体师”他杀案、悬而无果的 IT 男肺炸案背后的秘密。经历了这一系列变故的秦明最终成为了一名“为死者言，为生者权”的“生死语者”。",
        "name": "秦明·生死语者",
        "playUrl": "http://www.iqiyi.com/v_19rrdnxtyk.html",
        "isAdvance": false,
        "payMark": 1,
        "payMarkUrl": "http://pic0.iqiyipic.com/common/20171106/ac/1b/vip_100000_v_601.png",
        "imageUrl": "http://pic2.iqiyipic.com/image/20201014/79/f2/v_113814953_m_601_m9.jpg",
        "duration": "01:44:30",
        "videoCount": 1,
        "latestOrder": 1,
        "categories": [
          "普通话",
          "华语",
          "悬疑"
        ],
        "albumName": "秦明·生死语者",
        "albumImageUrl": "",
        "period": "2019-06-14",
        "exclusive": false,
        "qiyiProduced": false,
        "sourceId": 0,
        "focus": "《法医秦明》电影版",
        "people": {
          "main_charactor": [
            {
              "id": 214377505,
              "name": "严屹宽"
            },
            {
              "id": 233593505,
              "name": "代斯"
            },
            {
              "id": 214940905,
              "name": "耿乐"
            }
          ]
        },
        "score": 7.8,
        "imageSize": [
          "160_90",
          "220_124",
          "284_160",
          "320_180",
          "480_270",
          "1080_608",
          "1248_702",
          "832_468",
          "592_333",
          "480_360",
          "195_260",
          "260_360",
          "579_772",
          "318_424",
          "255_340",
          "141_188",
          "128_128",
          "580_435"
        ],
        "imageProductionType": [
          "IMAGE_PRODUCTION_TYPE_PREPARATION",
          "IMAGE_PRODUCTION_TYPE_ON_DEMAND"
        ],
        "title": "秦明·生死语者",
        "pingback": {
          "doc_id": 825571200
        }
      },
      {
        "tvId": 732638100,
        "albumId": 732638100,
        "channelId": 1,
        "description": "一声响指，宇宙间半数生命灰飞烟灭。几近绝望的复仇者们在惊奇队长的帮助下找到灭霸归隐之处，却得知六颗无限宝石均被销毁，希望彻底破灭。如是过了五年，迷失在量子领域的蚁人意外回到现实世界，他的出现为幸存的复仇者们点燃了希望。与美国队长冰释前嫌的托尼找到了穿越时空的方法，星散各地的超级英雄再度集结，他们分别穿越不同的时代去搜集无限宝石。而在这一过程中，平行宇宙的灭霸察觉了他们的计划。 ",
        "name": "复仇者联盟4：终局之战",
        "playUrl": "http://www.iqiyi.com/v_19rr7q1fy0.html",
        "isAdvance": false,
        "payMark": 1,
        "payMarkUrl": "http://pic0.iqiyipic.com/common/20171106/ac/1b/vip_100000_v_601.png",
        "imageUrl": "http://pic4.iqiyipic.com/image/20200908/90/6d/v_112869925_m_601_m32.jpg",
        "duration": "02:54:06",
        "videoCount": 1,
        "latestOrder": 1,
        "categories": [
          "科幻",
          "巨制",
          "奇幻"
        ],
        "albumName": "复仇者联盟4：终局之战",
        "albumImageUrl": "",
        "period": "2019-04-24",
        "exclusive": false,
        "qiyiProduced": false,
        "sourceId": 0,
        "focus": "漫威十年·英雄集结",
        "people": {
          "main_charactor": [
            {
              "id": 214958805,
              "name": "小罗伯特·唐尼"
            },
            {
              "id": 214721605,
              "name": "乔什·布洛林"
            },
            {
              "id": 214803405,
              "name": "马克·鲁弗洛"
            }
          ]
        },
        "score": 8.6,
        "imageSize": [
          "580_435",
          "128_128",
          "195_260",
          "260_360",
          "579_772",
          "318_424",
          "255_340",
          "141_188",
          "480_360",
          "160_90",
          "220_124",
          "284_160",
          "320_180",
          "480_270",
          "1080_608",
          "1248_702",
          "832_468",
          "592_333"
        ],
        "imageProductionType": [
          "IMAGE_PRODUCTION_TYPE_PREPARATION",
          "IMAGE_PRODUCTION_TYPE_ON_DEMAND"
        ],
        "title": "复仇者联盟4:终局之战",
        "pingback": {
          "doc_id": 732638100
        }
      },
      {
        "tvId": 8659881680241500,
        "albumId": 8659881680241500,
        "channelId": 1,
        "description": "青云堂女掌门于胜男是个拳头比铁硬、性子比钢直的泼辣女子。为了完成病重在床的父亲的愿望，急于结婚的于胜男在荒唐又搞笑的相亲路上认识了命定冤家牛多多，威逼利诱这个憨大叔和自己签下假结婚协议，带着他去民政局领了证。就在于胜男逐渐被牛多多的善良淳朴打动之际，多年前被于胜男父亲逐出师门的师兄林杰归来，以言语相激导致老人病发去世，又以牛多多的一条腿威胁于胜男接受挑战帖。于胜男怒而迎战，反目成仇的师兄妹誓要在武林大会上争个你死我活……",
        "name": "我的野蛮女掌门",
        "playUrl": "http://www.iqiyi.com/v_2d2dzb6fn00.html",
        "isAdvance": false,
        "payMark": 1,
        "payMarkUrl": "http://pic0.iqiyipic.com/common/20171106/ac/1b/vip_100000_v_601.png",
        "imageUrl": "http://pic0.iqiyipic.com/image/20210331/6f/71/v_158039975_m_601_m3.jpg",
        "duration": "01:34:52",
        "videoCount": 1,
        "latestOrder": 1,
        "categories": [
          "爱情",
          "喜剧",
          "功夫"
        ],
        "albumName": "我的野蛮女掌门",
        "albumImageUrl": "",
        "period": "2021-03-31",
        "exclusive": true,
        "qiyiProduced": false,
        "sourceId": 0,
        "focus": "暴力新娘武力逼婚",
        "people": {
          "main_charactor": [
            {
              "id": 215361105,
              "name": "于莎莎"
            },
            {
              "id": 231171505,
              "name": "王多多"
            },
            {
              "id": 215080705,
              "name": "杨政"
            }
          ]
        },
        "score": 8,
        "imageSize": [
          "160_90",
          "220_124",
          "284_160",
          "320_180",
          "480_270",
          "1080_608",
          "1248_702",
          "832_468",
          "592_333",
          "480_360",
          "195_260",
          "260_360",
          "579_772",
          "318_424",
          "255_340",
          "128_128"
        ],
        "imageProductionType": [
          "IMAGE_PRODUCTION_TYPE_PREPARATION",
          "IMAGE_PRODUCTION_TYPE_ON_DEMAND"
        ],
        "title": "我的野蛮女掌门",
        "pingback": {
          "doc_id": 8659881680241500
        }
      },
      {
        "tvId": 7357966509075200,
        "albumId": 7357966509075200,
        "channelId": 1,
        "description": "宏宇公司最新公测的VR游戏《恐龙世界》引来众多参与者，游戏和现实世界通过头盔相连，最终的幸存者可以获得500万的奖金，为争夺这份奖励，参与者不光要面对随时而来的恐龙的袭击，还要警惕其他玩家。很快，游戏里的三个老手迅速集结，靠着拼杀掠夺来的物资随意终结他人性命，连小孩也不放过，退役军人张琳集结其他两位，走上复仇之路。",
        "name": "恐龙世界",
        "playUrl": "http://www.iqiyi.com/v_20xw2u5tkz0.html",
        "isAdvance": false,
        "payMark": 0,
        "payMarkUrl": "",
        "imageUrl": "http://pic8.iqiyipic.com/image/20210429/a5/d5/v_154013193_m_601_m6.jpg",
        "duration": "01:01:22",
        "videoCount": 1,
        "latestOrder": 1,
        "categories": [
          "独播",
          "普通话",
          "英语"
        ],
        "albumName": "恐龙世界",
        "albumImageUrl": "",
        "period": "2020-10-23",
        "exclusive": true,
        "qiyiProduced": false,
        "sourceId": 0,
        "focus": "侏罗纪极致惊悚体验",
        "people": {
          "main_charactor": [
            {
              "id": 238713605,
              "name": "释彦能"
            },
            {
              "id": 203320105,
              "name": "左溢"
            }
          ]
        },
        "score": 7.3,
        "imageSize": [
          "160_90",
          "220_124",
          "284_160",
          "320_180",
          "480_270",
          "1080_608",
          "1248_702",
          "832_468",
          "592_333",
          "480_360",
          "195_260",
          "260_360",
          "579_772",
          "318_424",
          "255_340",
          "128_128"
        ],
        "imageProductionType": [
          "IMAGE_PRODUCTION_TYPE_ON_DEMAND",
          "IMAGE_PRODUCTION_TYPE_PREPARATION"
        ],
        "title": "恐龙世界",
        "pingback": {
          "doc_id": 7357966509075200
        }
      },
      {
        "tvId": 13040748800,
        "albumId": 13040748800,
        "channelId": 1,
        "description": "从小痴迷于研究雾隐门的罗刹镇捕头周同，原本和罗刹镇父母官县令周守义过着太平日子，不料却被镇中乡绅之子贾明与父亲贾有为联手设计陷害，使得周同父亲蒙冤入狱，周同侥幸逃脱途中偶遇奄奄一息的雾隐门天老，天老濒死之际将体内的“甲”传给周同，周同想凭借“甲”的力量救出父亲，却眼睁睁看着父亲被妖人毕方害死。周同被雾隐门救走，并跟随雾隐门学习奇门技法，在周同的刻苦努力下，最终成为雾隐门一员，与雾隐门合力斩妖除魔，让罗刹镇重新恢复太平....",
        "name": "奇门遁甲",
        "playUrl": "http://www.iqiyi.com/v_19rxcyu9nw.html",
        "isAdvance": false,
        "payMark": 0,
        "payMarkUrl": "",
        "imageUrl": "http://pic5.iqiyipic.com/image/20201124/44/7a/v_145276397_m_601_m25.jpg",
        "duration": "01:23:31",
        "videoCount": 1,
        "latestOrder": 1,
        "categories": [
          "奇幻",
          "普通话",
          "华语"
        ],
        "albumName": "奇门遁甲",
        "albumImageUrl": "",
        "period": "2020-03-19",
        "exclusive": true,
        "qiyiProduced": false,
        "sourceId": 0,
        "focus": "美艳蛇妖斗法天师",
        "people": {
          "main_charactor": [
            {
              "id": 243841605,
              "name": "贺鹏"
            },
            {
              "id": 234242005,
              "name": "林妍柔"
            },
            {
              "id": 207032205,
              "name": "高雄"
            }
          ]
        },
        "score": 7.8,
        "imageSize": [
          "128_128",
          "195_260",
          "260_360",
          "579_772",
          "318_424",
          "255_340",
          "480_360",
          "160_90",
          "220_124",
          "284_160",
          "320_180",
          "480_270",
          "1080_608",
          "1248_702",
          "832_468",
          "592_333"
        ],
        "imageProductionType": [
          "IMAGE_PRODUCTION_TYPE_PREPARATION",
          "IMAGE_PRODUCTION_TYPE_ON_DEMAND"
        ],
        "title": "奇门遁甲",
        "pingback": {
          "doc_id": 13040748800
        }
      },
      {
        "tvId": 1557500000,
        "albumId": 1557500000,
        "channelId": 1,
        "description": "上世纪90年代，刑警钟诚受命追捕悍匪集团“老鹰帮”。这群悍匪犯下惊天连环劫案，训练有素且纪律严明，首领张隼更屡次恶意挑衅，矛头直指钟诚。为将“老鹰帮”捉拿归案，钟诚带领刑警小队咬死不放，誓与恶势力斗争到底。数年间，警匪上演了一次次紧张刺激的较量，悍匪愈加猖獗，警方步步逼近，双方展开殊死对决。",
        "name": "除暴",
        "playUrl": "http://www.iqiyi.com/v_19rr423swc.html",
        "isAdvance": false,
        "payMark": 1,
        "payMarkUrl": "http://pic0.iqiyipic.com/common/20171106/ac/1b/vip_100000_v_601.png",
        "imageUrl": "http://pic7.iqiyipic.com/image/20210102/c7/24/v_121229814_m_601_m12.jpg",
        "duration": "01:34:15",
        "videoCount": 1,
        "latestOrder": 1,
        "categories": [
          "粤语",
          "普通话",
          "华语"
        ],
        "albumName": "除暴",
        "albumImageUrl": "",
        "period": "2020-11-20",
        "exclusive": false,
        "qiyiProduced": false,
        "sourceId": 0,
        "focus": "王千源决战吴彦祖",
        "people": {
          "main_charactor": [
            {
              "id": 214812005,
              "name": "王千源"
            },
            {
              "id": 202629805,
              "name": "吴彦祖"
            },
            {
              "id": 227429305,
              "name": "春夏"
            }
          ]
        },
        "score": 8.5,
        "imageSize": [
          "160_90",
          "220_124",
          "284_160",
          "320_180",
          "480_270",
          "1080_608",
          "1248_702",
          "832_468",
          "592_333",
          "480_360",
          "195_260",
          "260_360",
          "579_772",
          "318_424",
          "255_340",
          "128_128"
        ],
        "imageProductionType": [
          "IMAGE_PRODUCTION_TYPE_PREPARATION",
          "IMAGE_PRODUCTION_TYPE_ON_DEMAND"
        ],
        "title": "除暴",
        "pingback": {
          "doc_id": 1557500000
        }
      },
      {
        "tvId": 7686854506499900,
        "albumId": 7686854506499900,
        "channelId": 1,
        "description": "龙族灭亡后，宝藏遗落在荒漠深处。每隔十年，龙族宝库入口浮现沙漠，吸引了一批身怀绝技的能人，他们被称作“沙漠猎人”。荒漠从此成为了一个猎人与财宝、怪兽并存的奇幻世界。\n想要获得宝藏，必须要找到伽蓝、恒罗、阿逾三块宝石放入鬼工球，方能打开宝库大门，获得永远享之不尽的财富。龙族唯一在世的公主纥奚晴带着鬼工球来到猎人客栈，重金聘请顶级猎人江流海，与之一同寻找宝藏。一段沙漠中的奇幻冒险之旅就此展开……",
        "name": "大冒险王之西域寻龙",
        "playUrl": "http://www.iqiyi.com/v_23gnfc27234.html",
        "isAdvance": false,
        "payMark": 0,
        "payMarkUrl": "",
        "imageUrl": "http://pic1.iqiyipic.com/image/20200922/21/77/v_152132662_m_601_m3.jpg",
        "duration": "01:07:04",
        "videoCount": 1,
        "latestOrder": 1,
        "categories": [
          "喜剧",
          "奇幻",
          "寻宝"
        ],
        "albumName": "大冒险王之西域寻龙",
        "albumImageUrl": "",
        "period": "2020-09-20",
        "exclusive": true,
        "qiyiProduced": false,
        "sourceId": 0,
        "focus": "美娇娘战狂暴巨龙",
        "people": {
          "main_charactor": [
            {
              "id": 215203505,
              "name": "李晨浩"
            },
            {
              "id": 245514405,
              "name": "张楚萱"
            }
          ]
        },
        "score": 7.9,
        "imageSize": [
          "160_90",
          "220_124",
          "284_160",
          "320_180",
          "480_270",
          "1080_608",
          "1248_702",
          "832_468",
          "592_333",
          "480_360",
          "195_260",
          "260_360",
          "579_772",
          "318_424",
          "255_340",
          "141_188",
          "128_128",
          "580_435"
        ],
        "imageProductionType": [
          "IMAGE_PRODUCTION_TYPE_PREPARATION",
          "IMAGE_PRODUCTION_TYPE_ON_DEMAND"
        ],
        "title": "大冒险王之西域寻龙",
        "pingback": {
          "doc_id": 7686854506499900
        }
      },
      {
        "tvId": 91709500,
        "albumId": 91709500,
        "channelId": 1,
        "description": "大好青年车文杰（刘德华 饰）邂逅了公司老板千金程乐儿（关之琳 饰），在乐儿好友Banana（邱淑贞 饰）的撮合下两人迅速陷入热恋。乐儿前男友金默基（李子雄 饰）得知情况后，马上对车文杰产生敌意，聘请整蛊专家古晶（周星驰 饰）作弄车文杰，让他一无所有。于是古晶假扮车文杰父亲车亲仁（吴孟达 饰）从大陆来的私生子，从中捣乱。古晶的到来令车文杰的生活打乱，一切事仿佛都在古晶的操控之中。但Banana发现了古晶的真实身份，劝古晶顾念车家父子对他的照顾，转过头帮忙车文杰对付金默基。",
        "name": "整蛊专家",
        "playUrl": "http://www.iqiyi.com/v_19rrj5a7v4.html",
        "isAdvance": false,
        "payMark": 1,
        "payMarkUrl": "http://pic0.iqiyipic.com/common/20171106/ac/1b/vip_100000_v_601.png",
        "imageUrl": "http://pic0.iqiyipic.com/image/20200902/16/09/v_50017095_m_601_m11.jpg",
        "duration": "01:47:29",
        "videoCount": 1,
        "latestOrder": 1,
        "categories": [
          "爱情",
          "喜剧",
          "普通话"
        ],
        "albumName": "整蛊专家",
        "albumImageUrl": "",
        "period": "1991-02-02",
        "exclusive": false,
        "qiyiProduced": false,
        "sourceId": 0,
        "focus": "星爷刘天王联手整蛊",
        "people": {
          "main_charactor": [
            {
              "id": 214380405,
              "name": "周星驰"
            },
            {
              "id": 200002105,
              "name": "刘德华"
            },
            {
              "id": 214939305,
              "name": "关之琳"
            }
          ]
        },
        "score": 9.1,
        "imageSize": [
          "128_128",
          "195_260",
          "260_360",
          "579_772",
          "318_424",
          "255_340",
          "141_188",
          "480_360",
          "160_90",
          "220_124",
          "284_160",
          "320_180",
          "480_270",
          "1080_608",
          "1248_702",
          "832_468",
          "592_333",
          "580_435"
        ],
        "imageProductionType": [
          "IMAGE_PRODUCTION_TYPE_PREPARATION",
          "IMAGE_PRODUCTION_TYPE_ON_DEMAND"
        ],
        "title": "整蛊专家",
        "pingback": {
          "doc_id": 91709500
        }
      },
      {
        "tvId": 6943246765801300,
        "albumId": 6943246765801300,
        "channelId": 1,
        "description": "1953年，抗美援朝战争进入最终阶段，志愿军在金城发动最后一场大型战役。为在指定时间到达，向 金城前线投放更多战力，志愿军战士们在物资匮乏、武装悬殊的情况下，不断抵御敌机狂轰滥炸，以血肉 之躯一次次修补战火中的木桥。一段鲜为人知的历史，在暗流涌动的金刚川上徐徐展开......",
        "name": "金刚川",
        "playUrl": "http://www.iqiyi.com/v_1wxrc961u0o.html",
        "isAdvance": false,
        "payMark": 1,
        "payMarkUrl": "http://pic0.iqiyipic.com/common/20171106/ac/1b/vip_100000_v_601.png",
        "imageUrl": "http://pic2.iqiyipic.com/image/20201216/5a/e1/v_153797380_m_601_m5.jpg",
        "duration": "02:01:54",
        "videoCount": 1,
        "latestOrder": 1,
        "categories": [
          "战争",
          "普通话",
          "华语"
        ],
        "albumName": "金刚川",
        "albumImageUrl": "",
        "period": "2020-10-23",
        "exclusive": false,
        "qiyiProduced": false,
        "sourceId": 0,
        "focus": "吴京张译血性抗敌",
        "people": {
          "main_charactor": [
            {
              "id": 203609805,
              "name": "张译"
            },
            {
              "id": 202599805,
              "name": "吴京"
            },
            {
              "id": 215451405,
              "name": "李九霄"
            }
          ]
        },
        "score": 8.9,
        "imageSize": [
          "160_90",
          "220_124",
          "284_160",
          "320_180",
          "480_270",
          "1080_608",
          "1248_702",
          "832_468",
          "592_333",
          "480_360",
          "195_260",
          "260_360",
          "579_772",
          "318_424",
          "255_340",
          "128_128"
        ],
        "imageProductionType": [
          "IMAGE_PRODUCTION_TYPE_PREPARATION",
          "IMAGE_PRODUCTION_TYPE_ON_DEMAND"
        ],
        "title": "金刚川",
        "pingback": {
          "doc_id": 6943246765801300
        }
      },
      {
        "tvId": 95391900,
        "albumId": 95391900,
        "channelId": 1,
        "description": "北漂女汪小菲来时尚杂志面试，女老板ZOE因丈夫出轨正闹离婚，无暇顾及，让她从实习生做起。该杂志约画家栾亦鸿拍摄时尚照片。在换衣间，亦鸿偷窥到跳舞的小菲，遭到后者痛击。两人不打不相识，亦鸿追求小菲，并帮其谋得了跳舞减肥班老师的职位。小菲刚开始对他产生好感时，却发现他的前女友柯敏竟然还在纠缠。一怒之下，小菲扯谎要嫁，逼得亦鸿在时尚发布会上发狂。几经周折，正当小菲下定决心，接受亦鸿时，后者却逃避现实，留信一封，去了纽约……",
        "name": "爱出色",
        "playUrl": "http://www.iqiyi.com/v_19rrjdqy28.html",
        "isAdvance": false,
        "payMark": 1,
        "payMarkUrl": "http://pic0.iqiyipic.com/common/20171106/ac/1b/vip_100000_v_601.png",
        "imageUrl": "http://pic9.iqiyipic.com/image/20210425/84/d3/v_50053919_m_601_m13.jpg",
        "duration": "01:41:10",
        "videoCount": 1,
        "latestOrder": 1,
        "categories": [
          "爱情",
          "喜剧",
          "普通话"
        ],
        "albumName": "爱出色",
        "albumImageUrl": "",
        "period": "2010-11-09",
        "exclusive": false,
        "qiyiProduced": false,
        "sourceId": 0,
        "focus": "姚晨献银幕初吻",
        "people": {
          "main_charactor": [
            {
              "id": 200046105,
              "name": "刘烨"
            },
            {
              "id": 202939405,
              "name": "姚晨"
            },
            {
              "id": 214734705,
              "name": "陈冲"
            }
          ]
        },
        "score": 8.5,
        "imageSize": [
          "160_90",
          "220_124",
          "284_160",
          "320_180",
          "480_270",
          "1080_608",
          "1248_702",
          "832_468",
          "592_333",
          "480_360",
          "195_260",
          "260_360",
          "579_772",
          "318_424",
          "255_340",
          "128_128"
        ],
        "imageProductionType": [
          "IMAGE_PRODUCTION_TYPE_ON_DEMAND",
          "IMAGE_PRODUCTION_TYPE_PREPARATION"
        ],
        "title": "爱出色",
        "pingback": {
          "doc_id": 95391900
        }
      },
      {
        "tvId": 2158245300,
        "albumId": 2158245300,
        "channelId": 1,
        "description": "倾覆沉没的钻井平台，顺流直冲的运油车头，直坠入海的满载客机。交通海上应急反应特勤队队长高谦（彭于晏 饰）、机长方宇凌（辛芷蕾 饰）和绞车手赵呈（王彦霖 饰）一次次带领队伍第一时间抵达，站在水火咆哮的最前面，守在危急撤离的最后面，用生命对抗天灾人祸。但在自然面前，特勤员毕竟没有超能力，血肉之躯踩在死亡边缘，真实的恐惧无数次让这些斗士颤抖、无助和气馁。而海上救援的字典里没有“退缩”。当你听见旋翼的轰鸣、洪亮的汽笛、马达的飞驰，那是他们无惧艰难险阻，舍己为人，谱写的一曲英雄之歌。",
        "name": "紧急救援",
        "playUrl": "http://www.iqiyi.com/v_19rsi1yn6g.html",
        "isAdvance": false,
        "payMark": 1,
        "payMarkUrl": "http://pic0.iqiyipic.com/common/20171106/ac/1b/vip_100000_v_601.png",
        "imageUrl": "http://pic5.iqiyipic.com/image/20210205/93/47/v_127016760_m_601_m24.jpg",
        "duration": "02:13:46",
        "videoCount": 1,
        "latestOrder": 1,
        "categories": [
          "普通话",
          "华语",
          "动作"
        ],
        "albumName": "紧急救援",
        "albumImageUrl": "",
        "period": "2020-12-18",
        "exclusive": false,
        "qiyiProduced": false,
        "sourceId": 0,
        "focus": "彭于晏惊险救援",
        "people": {
          "main_charactor": [
            {
              "id": 215341205,
              "name": "彭于晏"
            },
            {
              "id": 205041305,
              "name": "王彦霖"
            },
            {
              "id": 214647805,
              "name": "辛芷蕾"
            }
          ]
        },
        "score": 8.7,
        "imageSize": [
          "160_90",
          "220_124",
          "284_160",
          "320_180",
          "480_270",
          "1080_608",
          "1248_702",
          "832_468",
          "592_333",
          "480_360",
          "195_260",
          "260_360",
          "579_772",
          "318_424",
          "255_340",
          "128_128"
        ],
        "imageProductionType": [
          "IMAGE_PRODUCTION_TYPE_PREPARATION",
          "IMAGE_PRODUCTION_TYPE_ON_DEMAND"
        ],
        "title": "紧急救援",
        "pingback": {
          "doc_id": 2158245300
        }
      },
      {
        "tvId": 334254400,
        "albumId": 334254400,
        "channelId": 1,
        "description": "爱德华与妻子康妮是令人艳羡的一对，他们有一个8岁的儿子。他们结婚已有11年，日子过得平平淡淡却十分美满幸福。可是生活的一成不变使康妮开始有些厌倦了。正在此时，她邂逅了神秘男子，更一发不可收拾的爱上了这名陌生人。面对丈夫，康妮不得不一而再再而三的向丈夫撒谎，不知不觉间，她已陷身于危险之中。爱德华还是发现了妻子的异样，当他知道了妻子果真有越轨行为的时候，他疯狂得要知道妻子对他不忠的所有细节。无奈知道得越多越痛苦，接着他偷偷约见了妻子的情人……",
        "name": "不忠",
        "playUrl": "http://www.iqiyi.com/v_19rrn70w8c.html",
        "isAdvance": false,
        "payMark": 1,
        "payMarkUrl": "http://pic0.iqiyipic.com/common/20171106/ac/1b/vip_100000_v_601.png",
        "imageUrl": "http://pic2.iqiyipic.com/image/20201215/6f/c3/v_108792444_m_601_m9.jpg",
        "duration": "02:02:19",
        "videoCount": 1,
        "latestOrder": 1,
        "categories": [
          "家庭",
          "爱情",
          "英语"
        ],
        "albumName": "不忠",
        "albumImageUrl": "",
        "period": "2002-05-10",
        "exclusive": false,
        "qiyiProduced": false,
        "sourceId": 0,
        "focus": "不谙平淡女人最好得手",
        "people": {
          "main_charactor": [
            {
              "id": 207187605,
              "name": "黛安·莲恩"
            },
            {
              "id": 205182705,
              "name": "理查·基尔"
            },
            {
              "id": 214489205,
              "name": "奥利维·马丁内兹"
            }
          ]
        },
        "score": 7.8,
        "imageSize": [
          "160_90",
          "220_124",
          "284_160",
          "320_180",
          "480_270",
          "1080_608",
          "1248_702",
          "832_468",
          "592_333",
          "480_360",
          "195_260",
          "260_360",
          "579_772",
          "318_424",
          "255_340",
          "128_128"
        ],
        "imageProductionType": [
          "IMAGE_PRODUCTION_TYPE_PREPARATION",
          "IMAGE_PRODUCTION_TYPE_ON_DEMAND"
        ],
        "title": "不忠",
        "pingback": {
          "doc_id": 334254400
        }
      },
      {
        "tvId": 94546100,
        "albumId": 94546100,
        "channelId": 1,
        "description": "世界各地发生多宗少女失踪个案，幕后策划是Madame M ，她专门诱拐并训练貌美少女，令她们成为防不胜防的床上杀手。一群女孩被软禁在荒岛上进行地狱式的特训，钻研各类型的战斗知识及暗杀技巧。活泼开朗的海遥坚强沉郁的Katt先后抵达荒岛，二人在艰苦的考验中互相扶持。海遥及Katt执行任务，海遥负责色诱目标，然后以折断脊椎来杀死对方。",
        "name": "赤裸特工",
        "playUrl": "http://www.iqiyi.com/v_19rrjdb9w8.html",
        "isAdvance": false,
        "payMark": 0,
        "payMarkUrl": "",
        "imageUrl": "http://pic8.iqiyipic.com/image/20200908/7e/68/v_50045461_m_601_m12.jpg",
        "duration": "01:30:43",
        "videoCount": 1,
        "latestOrder": 1,
        "categories": [
          "爱情",
          "粤语",
          "普通话"
        ],
        "albumName": "赤裸特工",
        "albumImageUrl": "",
        "period": "2002-11-15",
        "exclusive": false,
        "qiyiProduced": false,
        "sourceId": 0,
        "focus": "赤裸美女暗杀奸佞",
        "people": {
          "main_charactor": [
            {
              "id": 202629805,
              "name": "吴彦祖"
            },
            {
              "id": 215121005,
              "name": "李美琪"
            },
            {
              "id": 214393105,
              "name": "Anya"
            }
          ]
        },
        "score": 8.5,
        "imageSize": [
          "580_435",
          "160_90",
          "220_124",
          "284_160",
          "320_180",
          "480_270",
          "1080_608",
          "1248_702",
          "832_468",
          "592_333",
          "480_360",
          "195_260",
          "260_360",
          "579_772",
          "318_424",
          "255_340",
          "141_188",
          "128_128"
        ],
        "imageProductionType": [
          "IMAGE_PRODUCTION_TYPE_PREPARATION",
          "IMAGE_PRODUCTION_TYPE_ON_DEMAND"
        ],
        "title": "赤裸特工",
        "pingback": {
          "doc_id": 94546100
        }
      },
      {
        "tvId": 3489922791456500,
        "albumId": 3489922791456500,
        "channelId": 1,
        "description": "《海绵宝宝：营救大冒险》讲述了海绵宝宝心爱的宠物小蜗被绑架后，海绵宝宝和派大星前往失落的大西洋城展开营救冒险的故事。在这场充满危险又妙趣横生的营救行动中，海绵宝宝和他的朋友们用实际行动证明了友谊的力量无限大！",
        "name": "海绵宝宝：营救大冒险",
        "playUrl": "http://www.iqiyi.com/v_xguhfh4wbc.html",
        "isAdvance": false,
        "payMark": 1,
        "payMarkUrl": "http://pic0.iqiyipic.com/common/20171106/ac/1b/vip_100000_v_601.png",
        "imageUrl": "http://pic8.iqiyipic.com/image/20201110/3e/13/v_153820316_m_601_m8.jpg",
        "duration": "01:31:35",
        "videoCount": 1,
        "latestOrder": 1,
        "categories": [
          "喜剧",
          "普通话",
          "美国"
        ],
        "albumName": "海绵宝宝：营救大冒险",
        "albumImageUrl": "",
        "period": "2020-08-14",
        "exclusive": false,
        "qiyiProduced": false,
        "sourceId": 0,
        "focus": "好兄弟嗨翻海底城",
        "people": {
          "main_charactor": [
            {
              "id": 231678105,
              "name": "陈浩"
            },
            {
              "id": 223481005,
              "name": "冯盛"
            },
            {
              "id": 239898605,
              "name": "张遥函"
            }
          ]
        },
        "score": 8.6,
        "imageSize": [
          "160_90",
          "220_124",
          "284_160",
          "320_180",
          "480_270",
          "1080_608",
          "1248_702",
          "832_468",
          "592_333",
          "480_360",
          "195_260",
          "260_360",
          "579_772",
          "318_424",
          "255_340",
          "141_188",
          "128_128",
          "580_435"
        ],
        "imageProductionType": [
          "IMAGE_PRODUCTION_TYPE_PREPARATION",
          "IMAGE_PRODUCTION_TYPE_ON_DEMAND"
        ],
        "title": "海绵宝宝:营救大冒险",
        "pingback": {
          "doc_id": 3489922791456500
        }
      },
      {
        "tvId": 6936027273492200,
        "albumId": 6936027273492200,
        "channelId": 1,
        "description": "老实刻板的理发师杜常勇丧偶后独自抚养女儿，只想让女儿继承自己的家族企业理发店，但女儿一心想参加节目《后起之秀》当大明星，对老土理发店根本不屑一顾。缺乏理解的父女二人代沟颇深，吵架已成家常便饭。又一次吵架后杜常勇去天台劝女儿回家，却一起被宇宙射线击中，父女醒来发现身体已经互换，没想到这一互换让两个人的生活产生了翻天覆地的变化。杜常勇拎着茶缸老气横秋的替女儿参加演出意外爆红，后来还拍摄了《男人能装》的封面照，风头一时无二。杜小晴也用年轻人的蓬勃活力给理发店开发出了宠物美容等新项目。通过设身处地的参与对方的工作与生活，父女二人终于达成了真正的理解，最终女儿也终于站在了心心念念的《后起之秀》舞台上，为父亲为家庭引吭高歌。",
        "name": "窈窕老爹",
        "playUrl": "http://www.iqiyi.com/v_1ws4pk8cvb8.html",
        "isAdvance": false,
        "payMark": 1,
        "payMarkUrl": "http://pic0.iqiyipic.com/common/20171106/ac/1b/vip_100000_v_601.png",
        "imageUrl": "http://pic6.iqiyipic.com/image/20210329/3c/69/v_157566461_m_601_m2.jpg",
        "duration": "01:28:36",
        "videoCount": 1,
        "latestOrder": 1,
        "categories": [
          "喜剧",
          "奇幻",
          "普通话"
        ],
        "albumName": "窈窕老爹",
        "albumImageUrl": "",
        "period": "2021-03-18",
        "exclusive": true,
        "qiyiProduced": false,
        "sourceId": 0,
        "focus": "耿护院重生改贴膜",
        "people": {
          "main_charactor": [
            {
              "id": 214753805,
              "name": "林雪"
            },
            {
              "id": 216012505,
              "name": "陈昊明"
            },
            {
              "id": 242998005,
              "name": "王成思"
            }
          ]
        },
        "score": 8.1,
        "imageSize": [
          "160_90",
          "220_124",
          "284_160",
          "320_180",
          "480_270",
          "1080_608",
          "1248_702",
          "832_468",
          "592_333",
          "480_360",
          "195_260",
          "260_360",
          "579_772",
          "318_424",
          "255_340",
          "128_128"
        ],
        "imageProductionType": [
          "IMAGE_PRODUCTION_TYPE_PREPARATION",
          "IMAGE_PRODUCTION_TYPE_ON_DEMAND"
        ],
        "title": "窈窕老爹",
        "pingback": {
          "doc_id": 6936027273492200
        }
      },
      {
        "tvId": 732606600,
        "albumId": 732606600,
        "channelId": 1,
        "description": "德国的战争机器在撤退。两名美国M 18坦克歼击车被送到铲除纳粹难改组中的哈尔茨山躲藏。",
        "name": "冰雪勇士3",
        "playUrl": "http://www.iqiyi.com/v_19rr7q3lyc.html",
        "isAdvance": false,
        "payMark": 0,
        "payMarkUrl": "",
        "imageUrl": "http://pic3.iqiyipic.com/image/20200914/cc/6d/v_112869610_m_601_m1.jpg",
        "duration": "01:37:31",
        "videoCount": 1,
        "latestOrder": 1,
        "categories": [
          "战争",
          "英语",
          "美国"
        ],
        "albumName": "冰雪勇士3",
        "albumImageUrl": "",
        "period": "2014-08-15",
        "exclusive": false,
        "qiyiProduced": false,
        "sourceId": 0,
        "focus": "战争中士兵的英勇顽强",
        "people": {
          "main_charactor": [
            {
              "id": 218746305,
              "name": "Adam Gregory"
            },
            {
              "id": 229224005,
              "name": "Timothy S. Shoemaker"
            },
            {
              "id": 229224105,
              "name": "迈克尔·托德·贝伦斯"
            }
          ]
        },
        "score": 8.2,
        "imageSize": [
          "160_90",
          "220_124",
          "284_160",
          "320_180",
          "480_270",
          "1080_608",
          "1248_702",
          "832_468",
          "592_333",
          "480_360",
          "195_260",
          "260_360",
          "579_772",
          "318_424",
          "255_340",
          "141_188",
          "128_128",
          "580_435"
        ],
        "imageProductionType": [
          "IMAGE_PRODUCTION_TYPE_PREPARATION",
          "IMAGE_PRODUCTION_TYPE_ON_DEMAND"
        ],
        "title": "冰雪勇士3",
        "pingback": {
          "doc_id": 732606600
        }
      },
      {
        "tvId": 5982252080151700,
        "albumId": 5982252080151700,
        "channelId": 1,
        "description": "费兰斯•高德勒20年前曾是叱咤风云的杀手，收山后他在巴黎开了一家餐馆，过着平静安宁的日子。某天，他定居在澳门的女儿爱莲一家遭到不明身份的杀手的袭击。女婿和两个外孙全部遇难，只有爱莲侥幸逃生。费兰斯得知消息后连忙从法国赶往澳门，在见到现场的惨状后，他决心不惜一切代价为女儿一家复仇。由于人生地不熟，费兰斯的调查毫无进展。偶然间，他在酒店遭遇一起暗杀事件，三个杀手阿鬼、阿柱和肥乐给他留下极深的印象。经过短暂的试探和接触，费兰斯决定雇佣阿鬼三人作为帮手。凭借爱莲留下的线索和在凶案现场的勘查，众人逐渐缩小包围圈，一场复仇战随即悄悄地展开，而幕后的阴谋也慢慢浮出水面……",
        "name": "暗标",
        "playUrl": "http://www.iqiyi.com/v_1ms66g6cl4o.html",
        "isAdvance": false,
        "payMark": 0,
        "payMarkUrl": "",
        "imageUrl": "http://pic8.iqiyipic.com/image/20200831/47/c1/v_152444645_m_601_m2.jpg",
        "duration": "01:28:23",
        "videoCount": 1,
        "latestOrder": 1,
        "categories": [
          "法语",
          "粤语",
          "英语"
        ],
        "albumName": "暗标",
        "albumImageUrl": "",
        "period": "2009-08-20",
        "exclusive": false,
        "qiyiProduced": false,
        "sourceId": 0,
        "focus": "为女复仇杀手再出江湖",
        "people": {
          "main_charactor": [
            {
              "id": 200276305,
              "name": "Johnny Hallyday"
            }
          ]
        },
        "score": 8,
        "imageSize": [
          "580_435",
          "128_128",
          "195_260",
          "260_360",
          "579_772",
          "318_424",
          "255_340",
          "141_188",
          "480_360",
          "160_90",
          "220_124",
          "284_160",
          "320_180",
          "480_270",
          "1080_608",
          "1248_702",
          "832_468",
          "592_333"
        ],
        "imageProductionType": [
          "IMAGE_PRODUCTION_TYPE_PREPARATION",
          "IMAGE_PRODUCTION_TYPE_ON_DEMAND"
        ],
        "title": "暗标",
        "pingback": {
          "doc_id": 5982252080151700
        }
      },
      {
        "tvId": 386905800,
        "albumId": 386905800,
        "channelId": 1,
        "description": "许诺和言蹊是大学校园里一对令人艳羡的情侣。许诺作为校内闻名的栀子花乐队的主唱和队友为成为职业出道不懈努力着，怀揣舞蹈梦想的言蹊和三位好友有机会获得出国深造的机会，就在梦想似乎触手可及的时候，现实中却遭遇到许多障碍。当言蹊面临崩溃边缘，许诺成为支持她的臂膀；为了让言蹊重新燃起希望， 许诺与队友决定为她准备一个意想不到的惊喜。而这个“惊喜”竟然让冲动的年轻人付出了不小的代价。",
        "name": "栀子花开",
        "playUrl": "http://www.iqiyi.com/v_19rro9skv8.html",
        "isAdvance": false,
        "payMark": 1,
        "payMarkUrl": "http://pic0.iqiyipic.com/common/20171106/ac/1b/vip_100000_v_601.png",
        "imageUrl": "http://pic0.iqiyipic.com/image/20210425/62/f3/v_109365221_m_601_m10.jpg",
        "duration": "01:43:05",
        "videoCount": 1,
        "latestOrder": 1,
        "categories": [
          "爱情",
          "喜剧",
          "普通话"
        ],
        "albumName": "栀子花开",
        "albumImageUrl": "",
        "period": "2015-07-10",
        "exclusive": false,
        "qiyiProduced": false,
        "sourceId": 0,
        "focus": "绚烂绽放的花样青春",
        "people": {
          "main_charactor": [
            {
              "id": 200409305,
              "name": "李易峰"
            },
            {
              "id": 214507405,
              "name": "张慧雯"
            },
            {
              "id": 205824405,
              "name": "蒋劲夫"
            }
          ]
        },
        "score": 8.5,
        "imageSize": [
          "160_90",
          "220_124",
          "284_160",
          "320_180",
          "480_270",
          "1080_608",
          "1248_702",
          "832_468",
          "592_333",
          "480_360",
          "195_260",
          "260_360",
          "579_772",
          "318_424",
          "255_340",
          "128_128"
        ],
        "imageProductionType": [
          "IMAGE_PRODUCTION_TYPE_PREPARATION",
          "IMAGE_PRODUCTION_TYPE_ON_DEMAND"
        ],
        "title": "栀子花开",
        "pingback": {
          "doc_id": 386905800
        }
      },
      {
        "tvId": 12520012500,
        "albumId": 12520012500,
        "channelId": 1,
        "description": "历经严酷考验，阿伦戴尔王国终于回归往日平静。艾莎女王、安娜公主以及他们的好友雪宝、克里斯托弗、驯鹿斯文过着平静安逸的生活。可是最近一段时间，艾莎总会被一段神秘的吟唱所困扰，为了追寻真相，她义无反顾踏上了征途。担心姐姐的安全，安娜和雪宝、克里斯托弗他们紧紧跟随。在那座常年被浓雾所笼罩的森林里，不仅藏着神秘的自然力量，更隐藏着关于阿伦戴尔王国、艾莎的魔法来源以及两位公主父母丧生等一系列的秘密。\n艾莎开启了一段寻找自我的旅程……",
        "name": "冰雪奇缘2（普通话）",
        "playUrl": "http://www.iqiyi.com/v_19rvnmxv3s.html",
        "isAdvance": false,
        "payMark": 1,
        "payMarkUrl": "http://pic0.iqiyipic.com/common/20171106/ac/1b/vip_100000_v_601.png",
        "imageUrl": "http://pic4.iqiyipic.com/image/20200908/bf/67/v_144855000_m_601_m10.jpg",
        "duration": "01:39:02",
        "videoCount": 1,
        "latestOrder": 1,
        "categories": [
          "喜剧",
          "普通话",
          "美国"
        ],
        "albumName": "冰雪奇缘2（普通话）",
        "albumImageUrl": "",
        "period": "2019-11-22",
        "exclusive": false,
        "qiyiProduced": false,
        "sourceId": 0,
        "focus": "动画巨制再续传奇",
        "people": {
          "main_charactor": [
            {
              "id": 201159605,
              "name": "克里斯汀·贝尔"
            },
            {
              "id": 201982805,
              "name": "伊迪娜·门泽尔"
            },
            {
              "id": 201865305,
              "name": "乔纳森·格罗夫"
            }
          ]
        },
        "score": 8.6,
        "imageSize": [
          "160_90",
          "220_124",
          "284_160",
          "320_180",
          "480_270",
          "1080_608",
          "1248_702",
          "832_468",
          "592_333",
          "480_360",
          "195_260",
          "260_360",
          "579_772",
          "318_424",
          "255_340",
          "141_188",
          "128_128",
          "580_435"
        ],
        "imageProductionType": [
          "IMAGE_PRODUCTION_TYPE_PREPARATION",
          "IMAGE_PRODUCTION_TYPE_ON_DEMAND"
        ],
        "title": "冰雪奇缘2(普通话)",
        "pingback": {
          "doc_id": 12520012500
        }
      },
      {
        "tvId": 733747800,
        "albumId": 733747800,
        "channelId": 1,
        "description": "六、七十年代的香港，警察贪污，黑道横行，正是陈华与喇叭、猫仔及一班兄弟最风光的日子。\n　　陈华被视为「慈云山十三太保」之首，气焰高涨；还结识了一生至爱可柔，共度人生最甜蜜的时光。可惜好景不常，陈华因私下贩毒而被帮会追杀，幸好在亦敌亦友的扫毒组组长哈雷帮助下，逃出生天，但却终究法网难逃。出狱后，遭逢父亲病逝及女友可柔失踪，无比自责的陈华，顿然觉悟前非，立志重新做人。他不但积极参与青少年戒毒工作，获得十大杰青荣誉；更把喇叭与猫仔拉回正途，又经常出手调停江湖纠纷，因而深受黑白两道所敬重。某次于日本出席戒毒讲座后，陈华与可柔在街头重遇。他一心再续前缘，但又能否轻易为自己的感情拆弹？ ",
        "name": "毒。诫",
        "playUrl": "http://www.iqiyi.com/v_19rr7pjg38.html",
        "isAdvance": false,
        "payMark": 1,
        "payMarkUrl": "http://pic0.iqiyipic.com/common/20171106/ac/1b/vip_100000_v_601.png",
        "imageUrl": "http://pic4.iqiyipic.com/image/20201021/bb/f2/v_112881077_m_601_m4.jpg",
        "duration": "01:41:24",
        "videoCount": 1,
        "latestOrder": 1,
        "categories": [
          "粤语",
          "普通话",
          "华语"
        ],
        "albumName": "毒。诫",
        "albumImageUrl": "",
        "period": "2017-05-12",
        "exclusive": false,
        "qiyiProduced": false,
        "sourceId": 0,
        "focus": "影帝齐聚联合破毒",
        "people": {
          "main_charactor": [
            {
              "id": 202379105,
              "name": "刘青云"
            },
            {
              "id": 200483905,
              "name": "古天乐"
            },
            {
              "id": 214782005,
              "name": "张晋"
            }
          ]
        },
        "score": 8.6,
        "imageSize": [
          "160_90",
          "220_124",
          "284_160",
          "320_180",
          "480_270",
          "1080_608",
          "1248_702",
          "832_468",
          "592_333",
          "480_360",
          "195_260",
          "260_360",
          "579_772",
          "318_424",
          "255_340",
          "141_188",
          "128_128",
          "580_435"
        ],
        "imageProductionType": [
          "IMAGE_PRODUCTION_TYPE_PREPARATION",
          "IMAGE_PRODUCTION_TYPE_ON_DEMAND"
        ],
        "title": "毒。诫",
        "pingback": {
          "doc_id": 733747800
        }
      },
      {
        "tvId": 517043600,
        "albumId": 517043600,
        "channelId": 1,
        "description": "冲锋车案件主谋李家俊设计逃脱警方控制，与幕后黑手汇合，联手策划更大阴谋。而现警务处长刘杰辉，前警务副处长李文彬，和资深大律师简奥伟被卷入其中，香港将面临更加大的危机……",
        "name": "寒战2",
        "playUrl": "http://www.iqiyi.com/v_19rrmd64u4.html",
        "isAdvance": false,
        "payMark": 1,
        "payMarkUrl": "http://pic0.iqiyipic.com/common/20171106/ac/1b/vip_100000_v_601.png",
        "imageUrl": "http://pic9.iqiyipic.com/image/20200905/f6/d3/v_110759531_m_601_m6.jpg",
        "duration": "01:49:53",
        "videoCount": 1,
        "latestOrder": 1,
        "categories": [
          "普通话",
          "华语",
          "悬疑"
        ],
        "albumName": "寒战2",
        "albumImageUrl": "",
        "period": "2016-07-08",
        "exclusive": false,
        "qiyiProduced": false,
        "sourceId": 0,
        "focus": "三大影帝身陷权力游戏",
        "people": {
          "main_charactor": [
            {
              "id": 214742205,
              "name": "郭富城"
            },
            {
              "id": 200053005,
              "name": "梁家辉"
            },
            {
              "id": 202712805,
              "name": "周润发"
            }
          ]
        },
        "score": 8.6,
        "imageSize": [
          "160_90",
          "220_124",
          "284_160",
          "320_180",
          "480_270",
          "1080_608",
          "1248_702",
          "832_468",
          "592_333",
          "480_360",
          "195_260",
          "260_360",
          "579_772",
          "318_424",
          "255_340",
          "141_188",
          "128_128",
          "580_435"
        ],
        "imageProductionType": [
          "IMAGE_PRODUCTION_TYPE_PREPARATION",
          "IMAGE_PRODUCTION_TYPE_ON_DEMAND"
        ],
        "title": "寒战2",
        "pingback": {
          "doc_id": 517043600
        }
      },
      {
        "tvId": 8302572000,
        "albumId": 8302572000,
        "channelId": 1,
        "description": "你听过一个有关警察、歌手、神经病和黑手党公主的故事吗？《猛禽小队和哈莉·奎茵》是一个只有哈莉·奎茵本人才能讲出来的超乎寻常的奇妙传奇。哥谭市最为凶残自大的恶棍罗曼·赛恩尼斯和他狂热的手下萨斯为了寻找一个年轻女孩卡斯，将这座城市翻了个底朝天。哈莉、女猎手、黑金丝雀和蕾妮·蒙托亚不期而遇，看似违和的四人组不得不团结一致、携手作战，才有可能打败罗曼",
        "name": "猛禽小队和哈莉·奎茵",
        "playUrl": "http://www.iqiyi.com/v_19rtpunq8c.html",
        "isAdvance": false,
        "payMark": 1,
        "payMarkUrl": "http://pic0.iqiyipic.com/common/20171106/ac/1b/vip_100000_v_601.png",
        "imageUrl": "http://pic3.iqiyipic.com/image/20201124/13/50/v_139095832_m_601_m5.jpg",
        "duration": "01:44:11",
        "videoCount": 1,
        "latestOrder": 1,
        "categories": [
          "英语",
          "美国",
          "动作"
        ],
        "albumName": "猛禽小队和哈莉·奎茵",
        "albumImageUrl": "",
        "period": "2020-02-07",
        "exclusive": false,
        "qiyiProduced": false,
        "sourceId": 0,
        "focus": "小丑女携DC女团出道",
        "people": {
          "main_charactor": [
            {
              "id": 225708805,
              "name": "玛歌特·罗比"
            },
            {
              "id": 201259505,
              "name": "Mary Elizabeth Winstead"
            },
            {
              "id": 215009105,
              "name": "伊万·麦克格雷格"
            }
          ]
        },
        "score": 8.4,
        "imageSize": [
          "160_90",
          "220_124",
          "284_160",
          "320_180",
          "480_270",
          "1080_608",
          "1248_702",
          "832_468",
          "592_333",
          "480_360",
          "195_260",
          "260_360",
          "579_772",
          "318_424",
          "255_340",
          "128_128"
        ],
        "imageProductionType": [
          "IMAGE_PRODUCTION_TYPE_PREPARATION",
          "IMAGE_PRODUCTION_TYPE_ON_DEMAND"
        ],
        "title": "猛禽小队和哈莉·奎茵",
        "pingback": {
          "doc_id": 8302572000
        }
      },
      {
        "tvId": 1549643000,
        "albumId": 1549643000,
        "channelId": 1,
        "description": "七个好友聚餐，有人提议大家玩一个将手机公开的游戏：与在场所有人分享当晚收到的每一通来电、每一条短信微信、甚至广告弹窗，由此掀开了一场啼笑皆非的情感风暴。数字时代，小小手机隐藏着无数秘密，当聚餐局变成“揭秘局”，当通讯工具化身定时炸弹，嬉笑打闹之后，甜蜜情侣和模范夫妻、多年死党之间还能真诚相待、美好如初吗？这场刺激的勇敢者游戏，你敢玩吗？\n",
        "name": "来电狂响",
        "playUrl": "http://www.iqiyi.com/v_19rr3xf05w.html",
        "isAdvance": false,
        "payMark": 0,
        "payMarkUrl": "",
        "imageUrl": "http://pic9.iqiyipic.com/image/20200904/99/77/v_121150918_m_601_m15.jpg",
        "duration": "01:42:57",
        "videoCount": 1,
        "latestOrder": 1,
        "categories": [
          "爱情",
          "普通话",
          "院线"
        ],
        "albumName": "来电狂响",
        "albumImageUrl": "",
        "period": "2018-12-28",
        "exclusive": false,
        "qiyiProduced": false,
        "sourceId": 0,
        "focus": "佟大为爱情受考验",
        "people": {
          "main_charactor": [
            {
              "id": 200080105,
              "name": "佟大为"
            },
            {
              "id": 208593805,
              "name": "马丽"
            },
            {
              "id": 206830005,
              "name": "霍思燕"
            }
          ]
        },
        "score": 8.7,
        "imageSize": [
          "128_128",
          "195_260",
          "260_360",
          "579_772",
          "318_424",
          "255_340",
          "141_188",
          "480_360",
          "160_90",
          "220_124",
          "284_160",
          "320_180",
          "480_270",
          "1080_608",
          "1248_702",
          "832_468",
          "592_333",
          "580_435"
        ],
        "imageProductionType": [
          "IMAGE_PRODUCTION_TYPE_PREPARATION",
          "IMAGE_PRODUCTION_TYPE_ON_DEMAND"
        ],
        "title": "来电狂响",
        "pingback": {
          "doc_id": 1549643000
        }
      },
      {
        "tvId": 103634900,
        "albumId": 103634900,
        "channelId": 1,
        "description": "《惊天动地》讲述了我军某摩步旅旅长唐新生于演习途中得知大地震发生，在通讯中断、没有得到上级指示的情况下，独自带领部队，赶往距离他们最近的映川县进行救援的故事。\n",
        "name": "惊天动地",
        "playUrl": "http://www.iqiyi.com/v_19rrk2m114.html",
        "isAdvance": false,
        "payMark": 1,
        "payMarkUrl": "http://pic0.iqiyipic.com/common/20171106/ac/1b/vip_100000_v_601.png",
        "imageUrl": "http://pic6.iqiyipic.com/image/20201027/0b/24/v_50136349_m_601_m13.jpg",
        "duration": "01:41:25",
        "videoCount": 1,
        "latestOrder": 1,
        "categories": [
          "普通话",
          "华语",
          "灾难"
        ],
        "albumName": "惊天动地",
        "albumImageUrl": "",
        "period": "2009-09-24",
        "exclusive": true,
        "qiyiProduced": false,
        "sourceId": 0,
        "focus": "“三惊”系列最后一部",
        "people": {
          "main_charactor": [
            {
              "id": 204163605,
              "name": "李幼斌"
            },
            {
              "id": 202063805,
              "name": "侯勇"
            },
            {
              "id": 214656305,
              "name": "岳红"
            }
          ]
        },
        "score": 9,
        "imageSize": [
          "160_90",
          "220_124",
          "284_160",
          "320_180",
          "480_270",
          "1080_608",
          "1248_702",
          "832_468",
          "592_333",
          "480_360",
          "195_260",
          "260_360",
          "579_772",
          "318_424",
          "255_340",
          "141_188",
          "128_128",
          "580_435"
        ],
        "imageProductionType": [
          "IMAGE_PRODUCTION_TYPE_PREPARATION",
          "IMAGE_PRODUCTION_TYPE_ON_DEMAND"
        ],
        "title": "惊天动地",
        "pingback": {
          "doc_id": 103634900
        }
      },
      {
        "tvId": 6788044500,
        "albumId": 6788044500,
        "channelId": 1,
        "description": "以通缉犯徐糠伏尸屋事件开始，负责调查的警官林法栋发现涉及一宗一个月前的劫案，当中同谋包括汪新元、红毛与欧阳，而犯罪现场唯一目击证人是一只鹦鹉，林法栋锁定汪新元为嫌犯。不过案情卻不如想像中直接…",
        "name": "犯罪现场",
        "playUrl": "http://www.iqiyi.com/v_19rumnl320.html",
        "isAdvance": false,
        "payMark": 1,
        "payMarkUrl": "http://pic0.iqiyipic.com/common/20171106/ac/1b/vip_100000_v_601.png",
        "imageUrl": "http://pic2.iqiyipic.com/image/20201124/b2/85/v_137654881_m_601_m11.jpg",
        "duration": "01:44:12",
        "videoCount": 1,
        "latestOrder": 1,
        "categories": [
          "粤语",
          "普通话",
          "华语"
        ],
        "albumName": "犯罪现场",
        "albumImageUrl": "",
        "period": "2019-10-12",
        "exclusive": false,
        "qiyiProduced": false,
        "sourceId": 0,
        "focus": "古天乐持枪扫街",
        "people": {
          "main_charactor": [
            {
              "id": 200483905,
              "name": "古天乐"
            },
            {
              "id": 203147505,
              "name": "宣萱"
            },
            {
              "id": 214538505,
              "name": "张继聪"
            }
          ]
        },
        "score": 8.5,
        "imageSize": [
          "128_128",
          "195_260",
          "260_360",
          "579_772",
          "318_424",
          "255_340",
          "480_360",
          "160_90",
          "220_124",
          "284_160",
          "320_180",
          "480_270",
          "1080_608",
          "1248_702",
          "832_468",
          "592_333"
        ],
        "imageProductionType": [
          "IMAGE_PRODUCTION_TYPE_PREPARATION",
          "IMAGE_PRODUCTION_TYPE_ON_DEMAND"
        ],
        "title": "犯罪现场",
        "pingback": {
          "doc_id": 6788044500
        }
      },
      {
        "tvId": 733982800,
        "albumId": 733982800,
        "channelId": 1,
        "description": "1937年淞沪会战的最后一役，“八百壮士”奉命坚守上海四行仓库，以少敌多顽强抵抗四天四夜。",
        "name": "八佰",
        "playUrl": "http://www.iqiyi.com/v_19rr7plcfw.html",
        "isAdvance": false,
        "payMark": 1,
        "payMarkUrl": "http://pic0.iqiyipic.com/common/20171106/ac/1b/vip_100000_v_601.png",
        "imageUrl": "http://pic0.iqiyipic.com/image/20201102/3b/62/v_112883426_m_601_m15.jpg",
        "duration": "02:28:26",
        "videoCount": 1,
        "latestOrder": 1,
        "categories": [
          "战争",
          "巨制",
          "普通话"
        ],
        "albumName": "八佰",
        "albumImageUrl": "",
        "period": "2020-08-21",
        "exclusive": false,
        "qiyiProduced": false,
        "sourceId": 0,
        "focus": "年度必看抗日大片",
        "people": {
          "main_charactor": [
            {
              "id": 214812005,
              "name": "王千源"
            },
            {
              "id": 203609805,
              "name": "张译"
            },
            {
              "id": 214332905,
              "name": "姜武"
            }
          ]
        },
        "score": 8.9,
        "imageSize": [
          "580_435",
          "128_128",
          "195_260",
          "260_360",
          "579_772",
          "318_424",
          "255_340",
          "141_188",
          "480_360",
          "160_90",
          "220_124",
          "284_160",
          "320_180",
          "480_270",
          "1080_608",
          "1248_702",
          "832_468",
          "592_333"
        ],
        "imageProductionType": [
          "IMAGE_PRODUCTION_TYPE_PREPARATION",
          "IMAGE_PRODUCTION_TYPE_ON_DEMAND"
        ],
        "title": "八佰",
        "pingback": {
          "doc_id": 733982800
        }
      },
      {
        "tvId": 5131956281747400,
        "albumId": 5131956281747400,
        "channelId": 1,
        "description": "郡主王萱在与寒族将军萧霁新婚的夜晚化身为鬼魅的修罗新娘，四处杀戮破坏，连青梅竹马的三皇子子珩都惧怕不已。但萧霁却不离不弃，与王萱共同寻找真相，没想到牵扯出背后更大的阴谋。",
        "name": "修罗新娘",
        "playUrl": "http://www.iqiyi.com/v_1eqd0fdseck.html",
        "isAdvance": false,
        "payMark": 1,
        "payMarkUrl": "http://pic0.iqiyipic.com/common/20171106/ac/1b/vip_100000_v_601.png",
        "imageUrl": "http://pic2.iqiyipic.com/image/20201203/3b/d0/v_154574816_m_601_m7.jpg",
        "duration": "01:19:43",
        "videoCount": 1,
        "latestOrder": 1,
        "categories": [
          "独播",
          "爱情",
          "奇幻"
        ],
        "albumName": "修罗新娘",
        "albumImageUrl": "",
        "period": "2020-11-26",
        "exclusive": true,
        "qiyiProduced": false,
        "sourceId": 0,
        "focus": "将军守护嗜血新娘",
        "people": {
          "main_charactor": [
            {
              "id": 214376505,
              "name": "俞灏明"
            },
            {
              "id": 240430405,
              "name": "王初伊"
            },
            {
              "id": 214599105,
              "name": "周海媚"
            }
          ]
        },
        "score": 8.1,
        "imageSize": [
          "160_90",
          "220_124",
          "284_160",
          "320_180",
          "480_270",
          "1080_608",
          "1248_702",
          "832_468",
          "592_333",
          "480_360",
          "195_260",
          "260_360",
          "579_772",
          "318_424",
          "255_340",
          "128_128"
        ],
        "imageProductionType": [
          "IMAGE_PRODUCTION_TYPE_PREPARATION",
          "IMAGE_PRODUCTION_TYPE_ON_DEMAND"
        ],
        "title": "修罗新娘",
        "pingback": {
          "doc_id": 5131956281747400
        }
      },
      {
        "tvId": 8759350245373100,
        "albumId": 8759350245373100,
        "channelId": 1,
        "description": "广州归来商人吴远受果农杨代山所托，牵线贩售他的桃子，他们低价收购5640次火车沿线农民的水果，以次充好，制成果酱、罐头，再将阿娜打造成网红小仙姐姐，让她担当代言推广产品，牟取暴利。 好景不长，很快产品便出现问题，主播出事，让他们迅速陷入严重的困境，经过重重困难，有喜有悲，最终.......",
        "name": "绿皮火车",
        "playUrl": "http://www.iqiyi.com/v_2f329gpdr5s.html",
        "isAdvance": false,
        "payMark": 1,
        "payMarkUrl": "http://pic0.iqiyipic.com/common/20171106/ac/1b/vip_100000_v_601.png",
        "imageUrl": "http://pic8.iqiyipic.com/image/20210406/86/bc/v_158173686_m_601_m3.jpg",
        "duration": "01:40:19",
        "videoCount": 1,
        "latestOrder": 1,
        "categories": [
          "喜剧",
          "普通话",
          "华语"
        ],
        "albumName": "绿皮火车",
        "albumImageUrl": "",
        "period": "2021-04-06",
        "exclusive": true,
        "qiyiProduced": false,
        "sourceId": 0,
        "focus": "小人物爆笑致富",
        "people": {
          "main_charactor": [
            {
              "id": 238259805,
              "name": "郑奇"
            },
            {
              "id": 203581305,
              "name": "张璐瑶"
            }
          ]
        },
        "score": 8.2,
        "imageSize": [
          "160_90",
          "220_124",
          "284_160",
          "320_180",
          "480_270",
          "1080_608",
          "1248_702",
          "832_468",
          "592_333",
          "480_360",
          "195_260",
          "260_360",
          "579_772",
          "318_424",
          "255_340",
          "128_128"
        ],
        "imageProductionType": [
          "IMAGE_PRODUCTION_TYPE_ON_DEMAND",
          "IMAGE_PRODUCTION_TYPE_PREPARATION"
        ],
        "title": "绿皮火车",
        "pingback": {
          "doc_id": 8759350245373100
        }
      },
      {
        "tvId": 733968700,
        "albumId": 733968700,
        "channelId": 1,
        "description": "在加勒比海，一个僻静的小岛屿，杰克逊和他的探险团队在水下洞穴挖掘失散多年的玛雅宝藏。深海潜水员突然意外的发现，一个古老邪恶致命的「掠食者」被唤醒。他们扰乱生物，唤醒一直冬眠超过10万年的掠食者「海神雷克斯」，杰克逊和岛屿社区的生存成员必须设法生存下去，等待救援的到来，当他们意识到军方打算轰炸「海神雷克斯」生物和屿岛，他们唯一的生存希望就是让它......",
        "name": "恐龙侵袭",
        "playUrl": "http://www.iqiyi.com/v_19rr7pkbww.html",
        "isAdvance": false,
        "payMark": 1,
        "payMarkUrl": "http://pic0.iqiyipic.com/common/20171106/ac/1b/vip_100000_v_601.png",
        "imageUrl": "http://pic5.iqiyipic.com/image/20210121/d3/9c/v_112883283_m_601_m2.jpg",
        "duration": "01:18:19",
        "videoCount": 1,
        "latestOrder": 1,
        "categories": [
          "科幻",
          "英语",
          "美国"
        ],
        "albumName": "恐龙侵袭",
        "albumImageUrl": "",
        "period": "2013-12-04",
        "exclusive": false,
        "qiyiProduced": false,
        "sourceId": 0,
        "focus": "人类大战食肉恐龙",
        "people": {
          "main_charactor": [
            {
              "id": 223102205,
              "name": "布莱恩·克劳斯"
            },
            {
              "id": 235324605,
              "name": "安妮·麦克代尼尔斯"
            }
          ]
        },
        "score": 7,
        "imageSize": [

        ],
        "title": "恐龙侵袭",
        "pingback": {
          "doc_id": 733968700
        }
      },
      {
        "tvId": 110962300,
        "albumId": 110962300,
        "channelId": 1,
        "description": "中国西南、与世隔绝、群山环抱中有个寨子，是个人皆长寿、规矩自成之地，清时皇帝赐名“长寿镇”。某日突爆传染病，地方官派医生前往诊治，他在镇子外发现奄奄一息的牛结实。进寨后，往日温厚的村民一反常态，不仅对牛结实拒施援手、避若瘟疫，更迁怒于医生多管闲事，老镇长亲自带着长寿镇医生和接生婆、油漆匠，老族长等人千万百计的阻挠医生对牛结实的救援，牛结实最终没能被救活，医生也找不到此人暴毙的原因。镇民们对医生的不欢迎不合作态度，令医生很沮丧，正当他准备离开的时候，无意中发现了一个被全镇民众一起隐藏在山崖上的一个秘密，带着重重疑惑医生决定暗中走访长寿镇，直到他偶遇一个男孩，长寿镇迷案的真相才一步步揭开。",
        "name": "杀生",
        "playUrl": "http://www.iqiyi.com/v_19rrk88e1c.html",
        "isAdvance": false,
        "payMark": 0,
        "payMarkUrl": "",
        "imageUrl": "http://pic8.iqiyipic.com/image/20200905/29/b0/v_50209623_m_601_m10.jpg",
        "duration": "01:46:53",
        "videoCount": 1,
        "latestOrder": 1,
        "categories": [
          "喜剧",
          "普通话",
          "华语"
        ],
        "albumName": "杀生",
        "albumImageUrl": "",
        "period": "2012-04-28",
        "exclusive": false,
        "qiyiProduced": false,
        "sourceId": 0,
        "focus": "看到的不一定就是真相",
        "people": {
          "main_charactor": [
            {
              "id": 214327805,
              "name": "黄渤"
            },
            {
              "id": 201956405,
              "name": "任达华"
            },
            {
              "id": 214779605,
              "name": "余男"
            }
          ]
        },
        "score": 8.7,
        "imageSize": [

        ],
        "title": "杀生",
        "pingback": {
          "doc_id": 110962300
        }
      },
      {
        "tvId": 14340143800,
        "albumId": 14340143800,
        "channelId": 1,
        "description": "本片讲述了由军人和地方人员共同研究国外飞来的飞行物，在研发过程中要面对各国的豺狼虎豹，然后组成了”利剑行动小组“在错综复杂的危险环境中，每名成员发挥各自智慧和特长，形成战无不胜的力量，在惊心动魄中，把国家赋予的使命向前推进。在进行了激烈的斗争后，我方拿到了飞行器的残壳。此后，展开殊死搏斗。",
        "name": "狼鹰",
        "playUrl": "http://www.iqiyi.com/v_19rx3yv93o.html",
        "isAdvance": false,
        "payMark": 0,
        "payMarkUrl": "",
        "imageUrl": "http://pic8.iqiyipic.com/image/20200902/ae/43/v_146510633_m_601_m9.jpg",
        "duration": "01:26:56",
        "videoCount": 1,
        "latestOrder": 1,
        "categories": [
          "普通话",
          "华语",
          "网络电影"
        ],
        "albumName": "狼鹰",
        "albumImageUrl": "",
        "period": "2020-04-28",
        "exclusive": true,
        "qiyiProduced": false,
        "sourceId": 0,
        "focus": "特种兵边境绝杀悍匪",
        "people": {
          "main_charactor": [
            {
              "id": 215225205,
              "name": "姜艺声"
            },
            {
              "id": 215152005,
              "name": "申奥"
            }
          ]
        },
        "score": 7.3,
        "imageSize": [
          "160_90",
          "220_124",
          "284_160",
          "320_180",
          "480_270",
          "1080_608",
          "1248_702",
          "832_468",
          "592_333",
          "480_360",
          "195_260",
          "260_360",
          "579_772",
          "318_424",
          "255_340",
          "141_188",
          "128_128",
          "580_435"
        ],
        "imageProductionType": [
          "IMAGE_PRODUCTION_TYPE_PREPARATION",
          "IMAGE_PRODUCTION_TYPE_ON_DEMAND"
        ],
        "title": "狼鹰",
        "pingback": {
          "doc_id": 14340143800
        }
      },
      {
        "tvId": 4349844580335100,
        "albumId": 4349844580335100,
        "channelId": 1,
        "description": "影片讲述了三十年前，乒坛老将杨国强，为照顾孙儿杨双喜，放弃了人生最重要比赛。如今杨国强患老年痴呆，杨双喜得知当年真相，感动不已。为了圆满爷爷的人生，他游说几个身怀绝技的民间乒乓球高手，带着爷爷踏上了夺冠征程。期间发生了各式各样的笑泪故事，却也让每个人找到了生活的意义所在。",
        "name": "陈翔六点半之民间高手",
        "playUrl": "http://www.iqiyi.com/v_15l56wc8byo.html",
        "isAdvance": false,
        "payMark": 1,
        "payMarkUrl": "http://pic0.iqiyipic.com/common/20171106/ac/1b/vip_100000_v_601.png",
        "imageUrl": "http://pic4.iqiyipic.com/image/20210129/3e/6b/v_155665575_m_601_m6.jpg",
        "duration": "01:57:44",
        "videoCount": 1,
        "latestOrder": 1,
        "categories": [
          "喜剧",
          "普通话",
          "华语"
        ],
        "albumName": "陈翔六点半之民间高手",
        "albumImageUrl": "",
        "period": "2020-12-30",
        "exclusive": false,
        "qiyiProduced": false,
        "sourceId": 0,
        "focus": "民间高手菜刀削球",
        "people": {
          "main_charactor": [
            {
              "id": 238387405,
              "name": "蘑菇头"
            },
            {
              "id": 238387205,
              "name": "妹大爷"
            },
            {
              "id": 224919405,
              "name": "陈翔"
            }
          ]
        },
        "score": 8.8,
        "imageSize": [
          "160_90",
          "220_124",
          "284_160",
          "320_180",
          "480_270",
          "1080_608",
          "1248_702",
          "832_468",
          "592_333",
          "480_360",
          "195_260",
          "260_360",
          "579_772",
          "318_424",
          "255_340",
          "128_128"
        ],
        "imageProductionType": [
          "IMAGE_PRODUCTION_TYPE_PREPARATION",
          "IMAGE_PRODUCTION_TYPE_ON_DEMAND"
        ],
        "title": "陈翔六点半之民间高手",
        "pingback": {
          "doc_id": 4349844580335100
        }
      },
      {
        "tvId": 733622300,
        "albumId": 733622300,
        "channelId": 1,
        "description": "1927年，北伐战争刚取得重大成果之际，国民党“右派”为夺权叛变革命，发动了疯狂的“清共”行动，短短数月，近31万进步同胞遭到残酷杀害，全国震惊，刚刚看到希望的中国即将再次陷入军阀混战和独裁专制的深渊。由于没有自己的武装力量，成立不足7年的中国共产党在国民党“右派”的疯 狂进攻下，几乎遭遇毁灭性打击。 血的教训使毛泽东、周恩来等党内进步分子认识到了“枪杆子里出政权”的硬道理。生死存亡之际，他们临危受命，冒着生命危险分赴湖南和南昌等地，联合朱德、贺龙、叶挺、刘伯承等一批爱国将领发动起义，誓要组建一支真正属于人民的军队。铁血铸军魂，舍己保家国，本片讲述的就是这一段慷慨悲壮的热血岁月……",
        "name": "建军大业",
        "playUrl": "http://www.iqiyi.com/v_19rr7pgfhs.html",
        "isAdvance": false,
        "payMark": 0,
        "payMarkUrl": "",
        "imageUrl": "http://pic8.iqiyipic.com/image/20200908/c1/76/v_112879814_m_601_m13.jpg",
        "duration": "02:12:40",
        "videoCount": 1,
        "latestOrder": 1,
        "categories": [
          "战争",
          "巨制",
          "普通话"
        ],
        "albumName": "建军大业",
        "albumImageUrl": "",
        "period": "2017-07-27",
        "exclusive": false,
        "qiyiProduced": false,
        "sourceId": 0,
        "focus": "群星再燃炽热军魂",
        "people": {
          "main_charactor": [
            {
              "id": 200046105,
              "name": "刘烨"
            },
            {
              "id": 214381605,
              "name": "朱亚文"
            },
            {
              "id": 215235805,
              "name": "黄志忠"
            }
          ]
        },
        "score": 8.9,
        "imageSize": [
          "580_435",
          "160_90",
          "220_124",
          "284_160",
          "320_180",
          "480_270",
          "1080_608",
          "1248_702",
          "832_468",
          "592_333",
          "480_360",
          "195_260",
          "260_360",
          "579_772",
          "318_424",
          "255_340",
          "141_188",
          "128_128"
        ],
        "imageProductionType": [
          "IMAGE_PRODUCTION_TYPE_PREPARATION",
          "IMAGE_PRODUCTION_TYPE_ON_DEMAND"
        ],
        "title": "建军大业",
        "pingback": {
          "doc_id": 733622300
        }
      },
      {
        "tvId": 441033000,
        "albumId": 441033000,
        "channelId": 1,
        "description": "刚刚经历了一段失败感情的卡莉决定换一个生活环境开始新的生活，于是，她入住了“碎片”大厦。果不其然，没过多久，卡莉就在此处结识了两个风流倜傥的男人杰克和泽克，通过这两个男人之口，卡莉发现了一个惊人的秘密，自己租住的房子的原房客系自杀身亡，而熟知此事的邻居也在不久之后于建筑内被害。在和泽克深入交往之后，卡莉发现他竟然就是这幢公寓的主人，而在公寓的角角落落里，布满了泽克设置的，用于满足他偷窥癖好的摄像头。一时间，杀害两名死者的凶手的嫌疑落在了泽克的身上，然而，这一切到底是假象还是事实？卡莉也无法判断。",
        "name": "偷窥",
        "playUrl": "http://www.iqiyi.com/v_19rrl56nno.html",
        "isAdvance": false,
        "payMark": 1,
        "payMarkUrl": "http://pic0.iqiyipic.com/common/20171106/ac/1b/vip_100000_v_601.png",
        "imageUrl": "http://pic8.iqiyipic.com/image/20201124/d4/4f/v_109951622_m_601_m8.jpg",
        "duration": "01:32:02",
        "videoCount": 1,
        "latestOrder": 1,
        "categories": [
          "爱情",
          "英语",
          "美国"
        ],
        "albumName": "偷窥",
        "albumImageUrl": "",
        "period": "1993-05-21",
        "exclusive": false,
        "qiyiProduced": false,
        "sourceId": 0,
        "focus": "偷窥无处不在",
        "people": {
          "main_charactor": [
            {
              "id": 214580705,
              "name": "莎朗·斯通"
            },
            {
              "id": 215250105,
              "name": "威廉·鲍德温"
            },
            {
              "id": 214636805,
              "name": "汤姆·贝伦杰"
            }
          ]
        },
        "score": 7.3,
        "imageSize": [
          "128_128",
          "195_260",
          "260_360",
          "579_772",
          "318_424",
          "255_340",
          "480_360",
          "160_90",
          "220_124",
          "284_160",
          "320_180",
          "480_270",
          "1080_608",
          "1248_702",
          "832_468",
          "592_333"
        ],
        "imageProductionType": [
          "IMAGE_PRODUCTION_TYPE_PREPARATION",
          "IMAGE_PRODUCTION_TYPE_ON_DEMAND"
        ],
        "title": "偷窥",
        "pingback": {
          "doc_id": 441033000
        }
      },
      {
        "tvId": 1233104200,
        "albumId": 1233104200,
        "channelId": 1,
        "description": "　《奎迪：英雄再起》讲述拳王奎迪迎战“父仇”对手，遭遇惨败跌入人生低谷，在教练洛奇和家人的帮助下，克服心理障碍重新振作的故事。",
        "name": "奎迪2：英雄再起",
        "playUrl": "http://www.iqiyi.com/v_19rqy2hdt0.html",
        "isAdvance": false,
        "payMark": 1,
        "payMarkUrl": "http://pic0.iqiyipic.com/common/20171106/ac/1b/vip_100000_v_601.png",
        "imageUrl": "http://pic4.iqiyipic.com/image/20201123/08/48/v_117961118_m_601_m10.jpg",
        "duration": "02:10:03",
        "videoCount": 1,
        "latestOrder": 1,
        "categories": [
          "英语",
          "美国",
          "动作"
        ],
        "albumName": "奎迪2：英雄再起",
        "albumImageUrl": "",
        "period": "2019-01-04",
        "exclusive": false,
        "qiyiProduced": false,
        "sourceId": 0,
        "focus": "拳王迎战“父仇”对手",
        "people": {
          "main_charactor": [
            {
              "id": 205933805,
              "name": "西尔维斯特·史泰龙"
            },
            {
              "id": 208932705,
              "name": "迈克尔·B·乔丹"
            },
            {
              "id": 201415405,
              "name": "菲利西亚·拉斯海德"
            }
          ]
        },
        "score": 8.5,
        "imageSize": [
          "160_90",
          "220_124",
          "284_160",
          "320_180",
          "480_270",
          "1080_608",
          "1248_702",
          "832_468",
          "592_333",
          "480_360",
          "195_260",
          "260_360",
          "579_772",
          "318_424",
          "255_340",
          "128_128"
        ],
        "imageProductionType": [
          "IMAGE_PRODUCTION_TYPE_PREPARATION",
          "IMAGE_PRODUCTION_TYPE_ON_DEMAND"
        ],
        "title": "奎迪2:英雄再起",
        "pingback": {
          "doc_id": 1233104200
        }
      },
      {
        "tvId": 1557505264317700,
        "albumId": 1557505264317700,
        "channelId": 1,
        "description": "2010年，苏格兰格拉斯哥，一种未知、恐怖的病毒肆意蔓延，大批人类感染，全身布满疱疹，溃烂流脓，最终在折磨中痛苦死去。由于缺少医疗设备和疫苗，短短一周内死亡人数成千上万。为抑制病毒蔓延，英国政府对苏格兰进行全面封锁，企图将病毒彻底隔离。在此之后，地球上其他地区的人们得到长达近三十年的平静，但在2035年某天，该死亡病毒再次于英国伦敦爆发。正当政府官员焦急万分之际，他们得到了一条令人振奋的消息。一张卫星照片显示，在苏格兰隔离区有生命存活的迹象。为了找到对抗病毒的办法，政府派出以伊登•辛克莱为首的科学队伍进入隔离区。伊登当年从疫区侥幸逃生，当她回到这片阔别将近三十年的故土时，却发现这里已经变成弱肉强食、蛮荒残暴的血肉战场。",
        "name": "末日侵袭",
        "playUrl": "http://www.iqiyi.com/v_gluy2mcei0.html",
        "isAdvance": false,
        "payMark": 1,
        "payMarkUrl": "http://pic0.iqiyipic.com/common/20171106/ac/1b/vip_100000_v_601.png",
        "imageUrl": "http://pic5.iqiyipic.com/image/20201001/b1/17/v_153541722_m_601_m1.jpg",
        "duration": "01:44:09",
        "videoCount": 1,
        "latestOrder": 1,
        "categories": [
          "战争",
          "英语",
          "美国"
        ],
        "albumName": "末日侵袭",
        "albumImageUrl": "",
        "period": "2008-03-14",
        "exclusive": false,
        "qiyiProduced": false,
        "sourceId": 0,
        "focus": "恐怖病毒侵袭人类",
        "people": {
          "main_charactor": [
            {
              "id": 205488205,
              "name": "Rhona Mitra"
            },
            {
              "id": 215732105,
              "name": "马尔科姆·麦克道威尔"
            },
            {
              "id": 214732305,
              "name": "鲍勃·霍斯金斯"
            }
          ]
        },
        "score": 8.3,
        "imageSize": [
          "160_90",
          "220_124",
          "284_160",
          "320_180",
          "480_270",
          "1080_608",
          "1248_702",
          "832_468",
          "592_333",
          "480_360",
          "195_260",
          "260_360",
          "579_772",
          "318_424",
          "255_340",
          "141_188",
          "128_128",
          "580_435"
        ],
        "imageProductionType": [
          "IMAGE_PRODUCTION_TYPE_PREPARATION",
          "IMAGE_PRODUCTION_TYPE_ON_DEMAND"
        ],
        "title": "末日侵袭",
        "pingback": {
          "doc_id": 1557505264317700
        }
      },
      {
        "tvId": 1353735300,
        "albumId": 1353735300,
        "channelId": 1,
        "description": "晚唐年间，国师发动民众大量捕蛇。前去刺杀国师的白蛇意外失忆，被捕蛇村少年救下。为帮助少女找回记忆，两人踏上了一段冒险旅程。冒险的过程让两人感情迅速升温，但少女蛇妖的身份也逐渐显露，另一边国师与蛇族之间不可避免的大战也即将打响，两人的爱情将要接受巨大考验。",
        "name": "白蛇：缘起",
        "playUrl": "http://www.iqiyi.com/v_19rr575vxk.html",
        "isAdvance": false,
        "payMark": 0,
        "payMarkUrl": "",
        "imageUrl": "http://pic8.iqiyipic.com/image/20200908/7d/45/v_119183912_m_601_m23.jpg",
        "duration": "01:38:42",
        "videoCount": 1,
        "latestOrder": 1,
        "categories": [
          "爱情",
          "奇幻",
          "普通话"
        ],
        "albumName": "白蛇：缘起",
        "albumImageUrl": "",
        "period": "2019-01-11",
        "exclusive": false,
        "qiyiProduced": false,
        "sourceId": 0,
        "focus": "国师蛇族巅峰对决",
        "people": {
          "main_charactor": [
            {
              "id": 228223105,
              "name": "杨天翔"
            },
            {
              "id": 203483905,
              "name": "张喆"
            },
            {
              "id": 239898605,
              "name": "张遥函"
            }
          ]
        },
        "score": 9,
        "imageSize": [
          "580_435",
          "160_90",
          "220_124",
          "284_160",
          "320_180",
          "480_270",
          "1080_608",
          "1248_702",
          "832_468",
          "592_333",
          "480_360",
          "195_260",
          "260_360",
          "579_772",
          "318_424",
          "255_340",
          "141_188",
          "128_128"
        ],
        "imageProductionType": [
          "IMAGE_PRODUCTION_TYPE_PREPARATION",
          "IMAGE_PRODUCTION_TYPE_ON_DEMAND"
        ],
        "title": "白蛇:缘起",
        "pingback": {
          "doc_id": 1353735300
        }
      },
      {
        "tvId": 4434874159860000,
        "albumId": 4434874159860000,
        "channelId": 1,
        "description": "上世纪80年代初的东北，爱慕同事周萌的工人刘海柱因帮扶弱者，打抱不平，招惹上了不良分子并给自己的家人朋友带来危险。在经历被坏人打伤，被工厂开除等人生低谷后，刘海柱重新站起来，在危难关头帮助民警捉拿了日渐嚣张的混混，维护了社区治安和稳定",
        "name": "东北往事：我叫刘海柱",
        "playUrl": "http://www.iqiyi.com/v_17ismck6q8c.html",
        "isAdvance": false,
        "payMark": 0,
        "payMarkUrl": "",
        "imageUrl": "http://pic1.iqiyipic.com/image/20201205/a6/d3/v_151275926_m_601_m8.jpg",
        "duration": "01:24:37",
        "videoCount": 1,
        "latestOrder": 1,
        "categories": [
          "独播",
          "喜剧",
          "普通话"
        ],
        "albumName": "东北往事：我叫刘海柱",
        "albumImageUrl": "",
        "period": "2020-09-03",
        "exclusive": true,
        "qiyiProduced": false,
        "sourceId": 0,
        "focus": "许君聪单挑恶棍",
        "people": {
          "main_charactor": [
            {
              "id": 227528005,
              "name": "许君聪"
            },
            {
              "id": 243905405,
              "name": "刘奔"
            },
            {
              "id": 7771884086283505,
              "name": "龚小钧"
            }
          ]
        },
        "score": 8.3,
        "imageSize": [
          "160_90",
          "220_124",
          "284_160",
          "320_180",
          "480_270",
          "1080_608",
          "1248_702",
          "832_468",
          "592_333",
          "480_360",
          "195_260",
          "260_360",
          "579_772",
          "318_424",
          "255_340",
          "128_128"
        ],
        "imageProductionType": [
          "IMAGE_PRODUCTION_TYPE_PREPARATION",
          "IMAGE_PRODUCTION_TYPE_ON_DEMAND"
        ],
        "title": "东北往事:我叫刘海柱",
        "pingback": {
          "doc_id": 4434874159860000
        }
      },
      {
        "tvId": 2479935100,
        "albumId": 2479935100,
        "channelId": 1,
        "description": "千寻和爸爸妈妈一同驱车前往新家，在郊外的小路上不慎进入了神秘的隧道——他们去到了另外一个诡异世界—一个中世纪的小镇。远处飘来食物的香味，爸爸妈妈大快朵颐，孰料之后变成了猪！这时小镇上渐渐来了许多样子古怪、半透明的人。 \n",
        "name": "千与千寻",
        "playUrl": "http://www.iqiyi.com/v_19rsmpr66o.html",
        "isAdvance": false,
        "payMark": 1,
        "payMarkUrl": "http://pic0.iqiyipic.com/common/20171106/ac/1b/vip_100000_v_601.png",
        "imageUrl": "http://pic5.iqiyipic.com/image/20200908/b9/f0/v_129742881_m_601_m10.jpg",
        "duration": "02:04:29",
        "videoCount": 1,
        "latestOrder": 1,
        "categories": [
          "日本",
          "奇幻",
          "日语"
        ],
        "albumName": "千与千寻",
        "albumImageUrl": "",
        "period": "2019-06-21",
        "exclusive": true,
        "qiyiProduced": false,
        "sourceId": 0,
        "focus": "宫崎骏经典免费看",
        "people": {
          "main_charactor": [
            {
              "id": 204532805,
              "name": "柊瑠美"
            },
            {
              "id": 202148505,
              "name": "入野自由"
            },
            {
              "id": 202841005,
              "name": "夏木真理"
            }
          ]
        },
        "score": 8.8,
        "imageSize": [
          "580_435",
          "160_90",
          "220_124",
          "284_160",
          "320_180",
          "480_270",
          "1080_608",
          "1248_702",
          "832_468",
          "592_333",
          "480_360",
          "195_260",
          "260_360",
          "579_772",
          "318_424",
          "255_340",
          "141_188",
          "128_128"
        ],
        "imageProductionType": [
          "IMAGE_PRODUCTION_TYPE_PREPARATION",
          "IMAGE_PRODUCTION_TYPE_ON_DEMAND"
        ],
        "title": "千与千寻",
        "pingback": {
          "doc_id": 2479935100
        }
      },
      {
        "tvId": 3802767472251400,
        "albumId": 3802767472251400,
        "channelId": 1,
        "description": "本片是2019年春节档收视排第十一名的《战狼犬》原班人马精心打造的催泪大片。影片主要讲述性格倔强的退伍军人老正在村民的大铁锅下救下一只流浪狗，本来经济拮据还替它看病，遭到了儿子春生、儿媳秋燕的抵触，全村人的不理解。狗狗用行动化解了误解，赢得了大家的喜爱，最终众人还发现了老正收养狗狗背后的惊天大秘密。",
        "name": "战犬出击",
        "playUrl": "http://www.iqiyi.com/v_12pouinp204.html",
        "isAdvance": false,
        "payMark": 1,
        "payMarkUrl": "http://pic0.iqiyipic.com/common/20171106/ac/1b/vip_100000_v_601.png",
        "imageUrl": "http://pic0.iqiyipic.com/image/20210111/d5/fc/v_156471447_m_601.jpg",
        "duration": "01:15:39",
        "videoCount": 1,
        "latestOrder": 1,
        "categories": [
          "独播",
          "普通话",
          "华语"
        ],
        "albumName": "战犬出击",
        "albumImageUrl": "",
        "period": "2021-01-26",
        "exclusive": true,
        "qiyiProduced": false,
        "sourceId": 0,
        "focus": "军人与战犬的情感大片",
        "people": {
          "main_charactor": [
            {
              "id": 237170405,
              "name": "吴桂洲"
            },
            {
              "id": 229092505,
              "name": "谭镁纶"
            },
            {
              "id": 214198305,
              "name": "张益"
            }
          ]
        },
        "score": 8.2,
        "imageSize": [
          "195_260",
          "260_360",
          "579_772",
          "318_424",
          "255_340",
          "160_90",
          "220_124",
          "284_160",
          "320_180",
          "480_270",
          "1080_608",
          "1248_702",
          "832_468",
          "592_333",
          "128_128",
          "480_360"
        ],
        "imageProductionType": [
          "IMAGE_PRODUCTION_TYPE_PREPARATION",
          "IMAGE_PRODUCTION_TYPE_ON_DEMAND"
        ],
        "title": "战犬出击",
        "pingback": {
          "doc_id": 3802767472251400
        }
      },
      {
        "tvId": 3896628800,
        "albumId": 3896628800,
        "channelId": 1,
        "description": "故事发生于封神大战后。姜子牙率领众神伐纣，赢得封神大战胜利，以为可以唤回世间安宁。然而，一切并未结束。一个偶然，姜子牙发现了原来“封神大战”之下酝酿着更大的阴谋。姜子牙开始踏上探寻真相的旅途......",
        "name": "姜子牙",
        "playUrl": "http://www.iqiyi.com/v_19rrp0pmb0.html",
        "isAdvance": false,
        "payMark": 1,
        "payMarkUrl": "http://pic0.iqiyipic.com/common/20171106/ac/1b/vip_100000_v_601.png",
        "imageUrl": "http://pic2.iqiyipic.com/image/20201118/0a/73/v_134762233_m_601_m21.jpg",
        "duration": "01:49:56",
        "videoCount": 1,
        "latestOrder": 1,
        "categories": [
          "奇幻",
          "普通话",
          "华语"
        ],
        "albumName": "姜子牙",
        "albumImageUrl": "",
        "period": "2020-10-01",
        "exclusive": false,
        "qiyiProduced": false,
        "sourceId": 0,
        "focus": "年度必看口碑国漫",
        "people": {
          "main_charactor": [
            {
              "id": 243473605,
              "name": "郑希"
            }
          ]
        },
        "score": 8.5,
        "imageSize": [
          "160_90",
          "220_124",
          "284_160",
          "320_180",
          "480_270",
          "1080_608",
          "1248_702",
          "832_468",
          "592_333",
          "480_360",
          "195_260",
          "260_360",
          "579_772",
          "318_424",
          "255_340",
          "128_128"
        ],
        "imageProductionType": [
          "IMAGE_PRODUCTION_TYPE_PREPARATION",
          "IMAGE_PRODUCTION_TYPE_ON_DEMAND"
        ],
        "title": "姜子牙",
        "pingback": {
          "doc_id": 3896628800
        }
      },
      {
        "tvId": 3395267221678400,
        "albumId": 3395267221678400,
        "channelId": 1,
        "description": "天下最好的铸刀师，南宫世家的家主南宫义，用黄金和天外陨铁铸出了一把威力无比但会摄人心魂的“狂刀”。就在他想毁刀的那夜，一个姓秦的刀客却大破南宫世家，抢走了妖刀。从此江湖上多了一个手持金色妖刀的杀人魔，掀起了腥风血雨，又因他杀人从来只用一刀，所以被江湖人称——秦一刀。 十七年前，黑白两道数十位高手联合绞杀秦一刀，却无人生还，秦一刀也人间蒸发，了无音信。 十七年后，皇帝昏庸，义军四起，天下大乱，恶罪丛生。一名叫做阿狗的乞丐却意外与妖刀结缘，在这个乱世展开了一段新的传奇。",
        "name": "狂刀",
        "playUrl": "http://www.iqiyi.com/v_yl1xp1fl7w.html",
        "isAdvance": false,
        "payMark": 1,
        "payMarkUrl": "http://pic0.iqiyipic.com/common/20171106/ac/1b/vip_100000_v_601.png",
        "imageUrl": "http://pic5.iqiyipic.com/image/20210202/39/a2/v_157046577_m_601.jpg",
        "duration": "01:30:51",
        "videoCount": 1,
        "latestOrder": 1,
        "categories": [
          "独播",
          "武侠",
          "奇幻"
        ],
        "albumName": "狂刀",
        "albumImageUrl": "",
        "period": "2021-02-26",
        "exclusive": true,
        "qiyiProduced": false,
        "sourceId": 0,
        "focus": "美艳刀魂摄人心魄",
        "people": {
          "main_charactor": [
            {
              "id": 245379605,
              "name": "黄劲棠"
            },
            {
              "id": 227713205,
              "name": "维妮"
            },
            {
              "id": 242097405,
              "name": "李丞汐"
            }
          ]
        },
        "score": 7.5,
        "imageSize": [
          "195_260",
          "260_360",
          "579_772",
          "318_424",
          "255_340",
          "160_90",
          "220_124",
          "284_160",
          "320_180",
          "480_270",
          "1080_608",
          "1248_702",
          "832_468",
          "592_333",
          "128_128",
          "480_360"
        ],
        "imageProductionType": [
          "IMAGE_PRODUCTION_TYPE_PREPARATION",
          "IMAGE_PRODUCTION_TYPE_ON_DEMAND"
        ],
        "title": "狂刀",
        "pingback": {
          "doc_id": 3395267221678400
        }
      },
      {
        "tvId": 3708111902292200,
        "albumId": 3708111902292200,
        "channelId": 1,
        "description": "旧生何梓峯带著四位大学同学来到即将要被杀校的母校德肓书院怀念一翻。该学府曾被日军佔领为军用实验室，历年也流传著许多可怕的灵异事件。\n罗校长和方老师分别带著他们在校内各处参观并解述历史。众人来到校内博物馆，看到战时日军资料时均感到无比兴奋。他们更在旧存刊物中，看到一本旧生日记，竟记录了过往旧生曾遇到的种种灵异事件，裡面更提到一宗学生神秘失踪事件，究竟内裡隐藏了什麽秘密？他们会否也遇上相同的灵异事件？",
        "name": "绑灵",
        "playUrl": "http://www.iqiyi.com/v_1104irxlchw.html",
        "isAdvance": false,
        "payMark": 1,
        "payMarkUrl": "http://pic0.iqiyipic.com/common/20171106/ac/1b/vip_100000_v_601.png",
        "imageUrl": "http://pic8.iqiyipic.com/image/20210324/d3/b2/v_157076744_m_601_m4.jpg",
        "duration": "01:21:13",
        "videoCount": 1,
        "latestOrder": 1,
        "categories": [
          "独播",
          "普通话",
          "华语"
        ],
        "albumName": "绑灵",
        "albumImageUrl": "",
        "period": "2019-09-05",
        "exclusive": true,
        "qiyiProduced": false,
        "sourceId": 0,
        "focus": "惠英红鬼后归来",
        "people": {
          "main_charactor": [
            {
              "id": 215335805,
              "name": "惠英红"
            },
            {
              "id": 215141305,
              "name": "陈家乐"
            },
            {
              "id": 240773005,
              "name": "夏嫣"
            }
          ]
        },
        "score": 7.3,
        "imageSize": [
          "160_90",
          "220_124",
          "284_160",
          "320_180",
          "480_270",
          "1080_608",
          "1248_702",
          "832_468",
          "592_333",
          "480_360",
          "195_260",
          "260_360",
          "579_772",
          "318_424",
          "255_340",
          "128_128"
        ],
        "imageProductionType": [
          "IMAGE_PRODUCTION_TYPE_ON_DEMAND",
          "IMAGE_PRODUCTION_TYPE_PREPARATION"
        ],
        "title": "绑灵",
        "pingback": {
          "doc_id": 3708111902292200
        }
      },
      {
        "tvId": 730538900,
        "albumId": 730538900,
        "channelId": 1,
        "description": "一对女孩维多利亚·迪桑和莉莉·迪桑的母亲被他们的父亲所杀，父亲也随即自杀并将两个女儿遗弃在树林里。五年后，她们被发现时状况极差，孤独、饥饿，她们对一切的肢体接触都会感到恐惧和抗拒，没人知道她们是如何在如此孤独的环境中存活的。叔叔卢卡斯和女友安娜贝尔收养了她们，原本平静的生活也就此打破。黑暗中，总有一个如影随形的亡魂，而这个想要置他们于死地的鬼魂，两个女孩叫她：妈妈。",
        "name": "妈妈（2013）",
        "playUrl": "http://www.iqiyi.com/v_19rr7racjc.html",
        "isAdvance": false,
        "payMark": 1,
        "payMarkUrl": "http://pic0.iqiyipic.com/common/20171106/ac/1b/vip_100000_v_601.png",
        "imageUrl": "http://pic6.iqiyipic.com/image/20200930/c4/77/v_112848847_m_601_m2.jpg",
        "duration": "01:35:50",
        "videoCount": 1,
        "latestOrder": 1,
        "categories": [
          "英语",
          "恐怖",
          "惊悚"
        ],
        "albumName": "妈妈（2013）",
        "albumImageUrl": "",
        "period": "2013-01-18",
        "exclusive": false,
        "qiyiProduced": false,
        "sourceId": 0,
        "focus": "“妈妈”争夺战",
        "people": {
          "main_charactor": [
            {
              "id": 214569705,
              "name": "梅根·查彭提尔"
            },
            {
              "id": 225708305,
              "name": "尼古拉·科斯特-瓦尔道"
            }
          ]
        },
        "score": 8.6,
        "imageSize": [
          "160_90",
          "220_124",
          "284_160",
          "320_180",
          "480_270",
          "1080_608",
          "1248_702",
          "832_468",
          "592_333",
          "480_360",
          "195_260",
          "260_360",
          "579_772",
          "318_424",
          "255_340",
          "141_188",
          "128_128",
          "580_435"
        ],
        "imageProductionType": [
          "IMAGE_PRODUCTION_TYPE_PREPARATION",
          "IMAGE_PRODUCTION_TYPE_ON_DEMAND"
        ],
        "title": "妈妈(2013)",
        "pingback": {
          "doc_id": 730538900
        }
      },
      {
        "tvId": 733625200,
        "albumId": 733625200,
        "channelId": 1,
        "description": "影片设置于未来世界，讲述侦探马克(弗兰克·格里罗饰)的儿子被外星飞船吸走，而他需解救儿子，并对抗无时不在的外星生物。\n",
        "name": "天际浩劫2",
        "playUrl": "http://www.iqiyi.com/v_19rr7pggf0.html",
        "isAdvance": false,
        "payMark": 1,
        "payMarkUrl": "http://pic0.iqiyipic.com/common/20171106/ac/1b/vip_100000_v_601.png",
        "imageUrl": "http://pic3.iqiyipic.com/image/20200915/b3/d9/v_112879840_m_601_m5.jpg",
        "duration": "01:44:57",
        "videoCount": 1,
        "latestOrder": 1,
        "categories": [
          "独播",
          "科幻",
          "英语"
        ],
        "albumName": "天际浩劫2",
        "albumImageUrl": "",
        "period": "2017-12-15",
        "exclusive": true,
        "qiyiProduced": false,
        "sourceId": 0,
        "focus": "人类对战外星怪兽",
        "people": {
          "main_charactor": [
            {
              "id": 214181005,
              "name": "安东尼奥·法加斯"
            },
            {
              "id": 202444905,
              "name": "Bojana Novakovic"
            },
            {
              "id": 215429405,
              "name": "弗兰克·格里罗"
            }
          ]
        },
        "score": 8.2,
        "imageSize": [
          "160_90",
          "220_124",
          "284_160",
          "320_180",
          "480_270",
          "1080_608",
          "1248_702",
          "832_468",
          "592_333",
          "480_360",
          "195_260",
          "260_360",
          "579_772",
          "318_424",
          "255_340",
          "141_188",
          "128_128",
          "580_435"
        ],
        "imageProductionType": [
          "IMAGE_PRODUCTION_TYPE_PREPARATION",
          "IMAGE_PRODUCTION_TYPE_ON_DEMAND"
        ],
        "title": "天际浩劫2",
        "pingback": {
          "doc_id": 733625200
        }
      },
      {
        "tvId": 2882295200,
        "albumId": 2882295200,
        "channelId": 1,
        "description": "中国商人秦国立在英国惨遭雇佣兵组织“北极狼”绑架，秦的女儿也卷入其中，遭到追杀。千钧一发之际，急先锋国际安保团队成为他们唯一的希望，由总指挥唐焕庭带领雷震宇、张凯旋、弥雅、神雕等组成的急先锋行动小组，上天入地，辗转全球各地施展惊险营救。解救人质的过程中，竟发现“北极狼”背后的犯罪集团还策划了一场惊天密谋…",
        "name": "急先锋",
        "playUrl": "http://www.iqiyi.com/v_19rs77glak.html",
        "isAdvance": false,
        "payMark": 1,
        "payMarkUrl": "http://pic0.iqiyipic.com/common/20171106/ac/1b/vip_100000_v_601.png",
        "imageUrl": "http://pic2.iqiyipic.com/image/20201113/c3/8f/v_131397337_m_601_m20.jpg",
        "duration": "01:47:21",
        "videoCount": 1,
        "latestOrder": 1,
        "categories": [
          "喜剧",
          "普通话",
          "华语"
        ],
        "albumName": "急先锋",
        "albumImageUrl": "",
        "period": "2020-09-30",
        "exclusive": false,
        "qiyiProduced": false,
        "sourceId": 0,
        "focus": "成龙杨洋硬核开战",
        "people": {
          "main_charactor": [
            {
              "id": 200019905,
              "name": "成龙"
            },
            {
              "id": 215007205,
              "name": "杨洋"
            },
            {
              "id": 205633105,
              "name": "艾伦"
            }
          ]
        },
        "score": 8.6,
        "imageSize": [
          "160_90",
          "220_124",
          "284_160",
          "320_180",
          "480_270",
          "1080_608",
          "1248_702",
          "832_468",
          "592_333",
          "480_360",
          "195_260",
          "260_360",
          "579_772",
          "318_424",
          "255_340",
          "141_188",
          "128_128",
          "580_435"
        ],
        "imageProductionType": [
          "IMAGE_PRODUCTION_TYPE_PREPARATION",
          "IMAGE_PRODUCTION_TYPE_ON_DEMAND"
        ],
        "title": "急先锋",
        "pingback": {
          "doc_id": 2882295200
        }
      },
      {
        "tvId": 367710700,
        "albumId": 367710700,
        "channelId": 1,
        "description": "在南疆围捕贩毒分子的行动中，特种部队狙击手冷锋公然违抗上级的命令，开枪射杀伤害了战友的暴徒武吉。这一行动令冷锋遭到军方禁闭甚至强制退伍的处罚，不过各特种部队精英组成超级特种部队战狼中队的中队长龙小云，却十分欣赏这个敢作敢为且业务过硬的血性男儿，于是将其召入自己的麾下。在新近的一次演习中，冷锋凭借冷静的判断力从老首长处拔得一城，并且成功击退了突然出现的狼群。谁知在毫无准备的情况下，战狼遭到了一伙荷枪实弹分子的袭击。原来武吉的哥哥敏登是一个冷酷无情的国际通缉犯，他手下豢养了一大批身怀绝技的雇佣兵。为了给弟弟报仇，敏登派出雇佣兵千里迢迢奔着冷锋而来。",
        "name": "战狼",
        "playUrl": "http://www.iqiyi.com/v_19rrnqxz7k.html",
        "isAdvance": false,
        "payMark": 0,
        "payMarkUrl": "",
        "imageUrl": "http://pic2.iqiyipic.com/image/20200905/db/56/v_109159633_m_601_m16.jpg",
        "duration": "01:30:05",
        "videoCount": 1,
        "latestOrder": 1,
        "categories": [
          "战争",
          "普通话",
          "华语"
        ],
        "albumName": "战狼",
        "albumImageUrl": "",
        "period": "2015-04-02",
        "exclusive": false,
        "qiyiProduced": false,
        "sourceId": 0,
        "focus": "国产军事动作开山之作",
        "people": {
          "main_charactor": [
            {
              "id": 202599805,
              "name": "吴京"
            },
            {
              "id": 214779605,
              "name": "余男"
            },
            {
              "id": 203854805,
              "name": "斯科特·阿金斯"
            }
          ]
        },
        "score": 9.1,
        "imageSize": [
          "160_90",
          "220_124",
          "284_160",
          "320_180",
          "480_270",
          "1080_608",
          "1248_702",
          "832_468",
          "592_333",
          "480_360",
          "195_260",
          "260_360",
          "579_772",
          "318_424",
          "255_340",
          "141_188",
          "128_128",
          "580_435"
        ],
        "imageProductionType": [
          "IMAGE_PRODUCTION_TYPE_PREPARATION",
          "IMAGE_PRODUCTION_TYPE_ON_DEMAND"
        ],
        "title": "战狼",
        "pingback": {
          "doc_id": 367710700
        }
      },
      {
        "tvId": 2352873700,
        "albumId": 2352873700,
        "channelId": 1,
        "description": "悍匪龙志强，在香港回归前，趁香港英政府不作为，而屡犯巨案，先后绑架富豪利家及雷家之长子，勒索超过二十亿元，事主怕被报复, 交赎款后都不敢报警。中国公安部极为关注，与香港警方合力，派香港警员何天卧底潜入龙志强犯罪团伙，发现他正策划绑架澳门富豪贺不凡，最终陆港警察合力勇擒龙志强，救出贺不凡。",
        "name": "追龙2：追缉大富豪",
        "playUrl": "http://www.iqiyi.com/v_19rsgss5mw.html",
        "isAdvance": false,
        "payMark": 1,
        "payMarkUrl": "http://pic0.iqiyipic.com/common/20171106/ac/1b/vip_100000_v_601.png",
        "imageUrl": "http://pic3.iqiyipic.com/image/20200908/ee/a0/v_128836345_m_601_m10.jpg",
        "duration": "01:42:26",
        "videoCount": 1,
        "latestOrder": 1,
        "categories": [
          "普通话",
          "华语",
          "动作"
        ],
        "albumName": "追龙2：追缉大富豪",
        "albumImageUrl": "",
        "period": "2019-06-06",
        "exclusive": false,
        "qiyiProduced": false,
        "sourceId": 0,
        "focus": "古天乐搏命梁家辉",
        "people": {
          "main_charactor": [
            {
              "id": 200053005,
              "name": "梁家辉"
            },
            {
              "id": 200483905,
              "name": "古天乐"
            },
            {
              "id": 215117905,
              "name": "林家栋"
            }
          ]
        },
        "score": 7.9,
        "imageSize": [
          "160_90",
          "220_124",
          "284_160",
          "320_180",
          "480_270",
          "1080_608",
          "1248_702",
          "832_468",
          "592_333",
          "480_360",
          "195_260",
          "260_360",
          "579_772",
          "318_424",
          "255_340",
          "141_188",
          "128_128",
          "580_435"
        ],
        "imageProductionType": [
          "IMAGE_PRODUCTION_TYPE_PREPARATION",
          "IMAGE_PRODUCTION_TYPE_ON_DEMAND"
        ],
        "title": "追龙2:追缉大富豪",
        "pingback": {
          "doc_id": 2352873700
        }
      }
    ],
    "service_latency": 14439,
    "result_num": "800+"
  }
}